[
    {
        "variable":"ii_shift",
        "studies involved":[
            "Alfano2018",
            "Roland2008"
        ],
        "studies_details":[
            {
                "study_id":"Alfano2018",
                "fixed_effect":{
                    "coef":-0.0,
                    "weight":0.513117284,
                    "ci_lower":null,
                    "ci_upper":null
                },
                "random_effect":{
                    "coef":0.0,
                    "weight":0.513117284,
                    "ci_lower":null,
                    "ci_upper":null
                }
            },
            {
                "study_id":"Roland2008",
                "fixed_effect":{
                    "coef":-0.0,
                    "weight":0.4861111111,
                    "ci_lower":null,
                    "ci_upper":null
                },
                "random_effect":{
                    "coef":0.0,
                    "weight":0.4861111111,
                    "ci_lower":null,
                    "ci_upper":null
                }
            }
        ],
        "fixed_effects":{
            "coef":[
                -3.5553480615,
                -0.0
            ],
            "pvalues":[
                null,
                null
            ],
            "rsquared":-44.0347490347,
            "aic":-124.1106711892,
            "bic":-126.7243768281
        },
        "random_effects":{
            "coef":[
                -3.5553480615,
                0.0,
                1.0
            ],
            "pvalues":[
                null,
                null,
                null
            ],
            "group_variance":null,
            "log_likelihood":null
        }
    },
    {
        "variable":"pi_avoid",
        "studies involved":[
            "Alfano2018",
            "Muller2015",
            "Roland2008",
            "Stock2010",
            "Vicari2016"
        ],
        "studies_details":[
            {
                "study_id":"Alfano2018",
                "fixed_effect":{
                    "coef":-0.2220174978,
                    "weight":0.513117284,
                    "ci_lower":-1.6590290914,
                    "ci_upper":1.2149940959
                },
                "random_effect":{
                    "coef":-0.1661492102,
                    "weight":0.513117284,
                    "ci_lower":-0.8918149164,
                    "ci_upper":0.5595164961
                }
            },
            {
                "study_id":"Muller2015",
                "fixed_effect":{
                    "coef":-0.2220174978,
                    "weight":0.7291666667,
                    "ci_lower":-1.6590290914,
                    "ci_upper":1.2149940959
                },
                "random_effect":{
                    "coef":-0.1661492102,
                    "weight":0.7291666667,
                    "ci_lower":-0.8918149164,
                    "ci_upper":0.5595164961
                }
            },
            {
                "study_id":"Roland2008",
                "fixed_effect":{
                    "coef":-0.2220174978,
                    "weight":0.4861111111,
                    "ci_lower":-1.6590290914,
                    "ci_upper":1.2149940959
                },
                "random_effect":{
                    "coef":-0.1661492102,
                    "weight":0.4861111111,
                    "ci_lower":-0.8918149164,
                    "ci_upper":0.5595164961
                }
            },
            {
                "study_id":"Stock2010",
                "fixed_effect":{
                    "coef":-0.2220174978,
                    "weight":4.0509259259,
                    "ci_lower":-1.6590290914,
                    "ci_upper":1.2149940959
                },
                "random_effect":{
                    "coef":-0.1661492102,
                    "weight":4.0509259259,
                    "ci_lower":-0.8918149164,
                    "ci_upper":0.5595164961
                }
            },
            {
                "study_id":"Vicari2016",
                "fixed_effect":{
                    "coef":-0.2220174978,
                    "weight":2.6417621788,
                    "ci_lower":-1.6590290914,
                    "ci_upper":1.2149940959
                },
                "random_effect":{
                    "coef":-0.1661492102,
                    "weight":2.6417621788,
                    "ci_lower":-0.8918149164,
                    "ci_upper":0.5595164961
                }
            }
        ],
        "fixed_effects":{
            "coef":[
                -3.3333305637,
                -0.2220174978
            ],
            "pvalues":[
                0.0003492461,
                0.7818111156
            ],
            "rsquared":0.0296598369,
            "aic":8.2149058723,
            "bic":7.4337816972
        },
        "random_effects":{
            "coef":[
                -3.3891988513,
                -0.1661492102,
                1.0
            ],
            "pvalues":[
                0.0,
                0.6536021029,
                null
            ],
            "group_variance":0.0552111201,
            "log_likelihood":-1.6447972079
        }
    },
    {
        "variable":"viral_breakthrough",
        "studies involved":[
            "Alfano2018",
            "Mazuecos2011",
            "Mazuecos2013",
            "Muller2015",
            "Roland2008",
            "Stock2010"
        ],
        "studies_details":[
            {
                "study_id":"Alfano2018",
                "fixed_effect":{
                    "coef":-0.3236892307,
                    "weight":0.513117284,
                    "ci_lower":-0.8469505934,
                    "ci_upper":0.1995721319
                },
                "random_effect":{
                    "coef":-0.2371613696,
                    "weight":0.513117284,
                    "ci_lower":-0.7498447834,
                    "ci_upper":0.2755220441
                }
            },
            {
                "study_id":"Mazuecos2011",
                "fixed_effect":{
                    "coef":-0.3236892307,
                    "weight":1.2014198692,
                    "ci_lower":-0.8469505934,
                    "ci_upper":0.1995721319
                },
                "random_effect":{
                    "coef":-0.2371613696,
                    "weight":1.2014198692,
                    "ci_lower":-0.7498447834,
                    "ci_upper":0.2755220441
                }
            },
            {
                "study_id":"Mazuecos2013",
                "fixed_effect":{
                    "coef":-0.3236892307,
                    "weight":1.0413028824,
                    "ci_lower":-0.8469505934,
                    "ci_upper":0.1995721319
                },
                "random_effect":{
                    "coef":-0.2371613696,
                    "weight":1.0413028824,
                    "ci_lower":-0.7498447834,
                    "ci_upper":0.2755220441
                }
            },
            {
                "study_id":"Muller2015",
                "fixed_effect":{
                    "coef":-0.3236892307,
                    "weight":0.7291666667,
                    "ci_lower":-0.8469505934,
                    "ci_upper":0.1995721319
                },
                "random_effect":{
                    "coef":-0.2371613696,
                    "weight":0.7291666667,
                    "ci_lower":-0.7498447834,
                    "ci_upper":0.2755220441
                }
            },
            {
                "study_id":"Roland2008",
                "fixed_effect":{
                    "coef":-0.3236892307,
                    "weight":0.4861111111,
                    "ci_lower":-0.8469505934,
                    "ci_upper":0.1995721319
                },
                "random_effect":{
                    "coef":-0.2371613696,
                    "weight":0.4861111111,
                    "ci_lower":-0.7498447834,
                    "ci_upper":0.2755220441
                }
            },
            {
                "study_id":"Stock2010",
                "fixed_effect":{
                    "coef":-0.3236892307,
                    "weight":4.0509259259,
                    "ci_lower":-0.8469505934,
                    "ci_upper":0.1995721319
                },
                "random_effect":{
                    "coef":-0.2371613696,
                    "weight":4.0509259259,
                    "ci_lower":-0.7498447834,
                    "ci_upper":0.2755220441
                }
            }
        ],
        "fixed_effects":{
            "coef":[
                -3.2316588308,
                -0.3236892307
            ],
            "pvalues":[
                0.0000871326,
                0.2920503305
            ],
            "rsquared":0.268744897,
            "aic":6.899852694,
            "bic":6.4833716325
        },
        "random_effects":{
            "coef":[
                -3.3181866918,
                -0.2371613696,
                1.0
            ],
            "pvalues":[
                null,
                0.3645796674,
                null
            ],
            "group_variance":0.0684205234,
            "log_likelihood":-2.7376043662
        }
    },
    {
        "variable":"hivan",
        "studies involved":[
            "Alfano2018",
            "Gathogo2017",
            "Muller2015",
            "Roland2008",
            "Stock2010",
            "Vicari2016"
        ],
        "studies_details":[
            {
                "study_id":"Alfano2018",
                "fixed_effect":{
                    "coef":-0.8737763196,
                    "weight":0.513117284,
                    "ci_lower":-2.0170429187,
                    "ci_upper":0.2694902794
                },
                "random_effect":{
                    "coef":-0.5208457475,
                    "weight":0.513117284,
                    "ci_lower":-0.5208457475,
                    "ci_upper":-0.5208457475
                }
            },
            {
                "study_id":"Gathogo2017",
                "fixed_effect":{
                    "coef":-0.8737763196,
                    "weight":1.0802469136,
                    "ci_lower":-2.0170429187,
                    "ci_upper":0.2694902794
                },
                "random_effect":{
                    "coef":-0.5208457475,
                    "weight":1.0802469136,
                    "ci_lower":-0.5208457475,
                    "ci_upper":-0.5208457475
                }
            },
            {
                "study_id":"Muller2015",
                "fixed_effect":{
                    "coef":-0.8737763196,
                    "weight":0.7291666667,
                    "ci_lower":-2.0170429187,
                    "ci_upper":0.2694902794
                },
                "random_effect":{
                    "coef":-0.5208457475,
                    "weight":0.7291666667,
                    "ci_lower":-0.5208457475,
                    "ci_upper":-0.5208457475
                }
            },
            {
                "study_id":"Roland2008",
                "fixed_effect":{
                    "coef":-0.8737763196,
                    "weight":0.4861111111,
                    "ci_lower":-2.0170429187,
                    "ci_upper":0.2694902794
                },
                "random_effect":{
                    "coef":-0.5208457475,
                    "weight":0.4861111111,
                    "ci_lower":-0.5208457475,
                    "ci_upper":-0.5208457475
                }
            },
            {
                "study_id":"Stock2010",
                "fixed_effect":{
                    "coef":-0.8737763196,
                    "weight":4.0509259259,
                    "ci_lower":-2.0170429187,
                    "ci_upper":0.2694902794
                },
                "random_effect":{
                    "coef":-0.5208457475,
                    "weight":4.0509259259,
                    "ci_lower":-0.5208457475,
                    "ci_upper":-0.5208457475
                }
            },
            {
                "study_id":"Vicari2016",
                "fixed_effect":{
                    "coef":-0.8737763196,
                    "weight":2.6417621788,
                    "ci_lower":-2.0170429187,
                    "ci_upper":0.2694902794
                },
                "random_effect":{
                    "coef":-0.5208457475,
                    "weight":2.6417621788,
                    "ci_lower":-0.5208457475,
                    "ci_upper":-0.5208457475
                }
            }
        ],
        "fixed_effects":{
            "coef":[
                -3.1321815813,
                -0.8737763196
            ],
            "pvalues":[
                0.0000948188,
                0.2084946484
            ],
            "rsquared":0.3593822531,
            "aic":5.8326690134,
            "bic":5.4161879518
        },
        "random_effects":{
            "coef":[
                -3.2587819647,
                -0.5208457475,
                1.0
            ],
            "pvalues":[
                9.481487061e-207,
                0.0,
                null
            ],
            "group_variance":0.0338395977,
            "log_likelihood":-0.6732988019
        }
    },
    {
        "variable":"hcv",
        "studies involved":[
            "Alfano2018",
            "Gathogo2017",
            "Locke2009",
            "Mazuecos2011",
            "Mazuecos2013",
            "Roland2008",
            "Vicari2016"
        ],
        "studies_details":[
            {
                "study_id":"Alfano2018",
                "fixed_effect":{
                    "coef":-0.2433201417,
                    "weight":0.513117284,
                    "ci_lower":-1.7359531881,
                    "ci_upper":1.2493129046
                },
                "random_effect":{
                    "coef":-0.1830433381,
                    "weight":0.513117284,
                    "ci_lower":-0.6164112738,
                    "ci_upper":0.2503245976
                }
            },
            {
                "study_id":"Gathogo2017",
                "fixed_effect":{
                    "coef":-0.2433201417,
                    "weight":1.0802469136,
                    "ci_lower":-1.7359531881,
                    "ci_upper":1.2493129046
                },
                "random_effect":{
                    "coef":-0.1830433381,
                    "weight":1.0802469136,
                    "ci_lower":-0.6164112738,
                    "ci_upper":0.2503245976
                }
            },
            {
                "study_id":"Locke2009",
                "fixed_effect":{
                    "coef":-0.2433201417,
                    "weight":2.700617284,
                    "ci_lower":-1.7359531881,
                    "ci_upper":1.2493129046
                },
                "random_effect":{
                    "coef":-0.1830433381,
                    "weight":2.700617284,
                    "ci_lower":-0.6164112738,
                    "ci_upper":0.2503245976
                }
            },
            {
                "study_id":"Mazuecos2011",
                "fixed_effect":{
                    "coef":-0.2433201417,
                    "weight":1.2014198692,
                    "ci_lower":-1.7359531881,
                    "ci_upper":1.2493129046
                },
                "random_effect":{
                    "coef":-0.1830433381,
                    "weight":1.2014198692,
                    "ci_lower":-0.6164112738,
                    "ci_upper":0.2503245976
                }
            },
            {
                "study_id":"Mazuecos2013",
                "fixed_effect":{
                    "coef":-0.2433201417,
                    "weight":1.0413028824,
                    "ci_lower":-1.7359531881,
                    "ci_upper":1.2493129046
                },
                "random_effect":{
                    "coef":-0.1830433381,
                    "weight":1.0413028824,
                    "ci_lower":-0.6164112738,
                    "ci_upper":0.2503245976
                }
            },
            {
                "study_id":"Roland2008",
                "fixed_effect":{
                    "coef":-0.2433201417,
                    "weight":0.4861111111,
                    "ci_lower":-1.7359531881,
                    "ci_upper":1.2493129046
                },
                "random_effect":{
                    "coef":-0.1830433381,
                    "weight":0.4861111111,
                    "ci_lower":-0.6164112738,
                    "ci_upper":0.2503245976
                }
            },
            {
                "study_id":"Vicari2016",
                "fixed_effect":{
                    "coef":-0.2433201417,
                    "weight":2.6417621788,
                    "ci_lower":-1.7359531881,
                    "ci_upper":1.2493129046
                },
                "random_effect":{
                    "coef":-0.1830433381,
                    "weight":2.6417621788,
                    "ci_lower":-0.6164112738,
                    "ci_upper":0.2503245976
                }
            }
        ],
        "fixed_effects":{
            "coef":[
                -3.1878653819,
                -0.2433201417
            ],
            "pvalues":[
                0.0000738836,
                0.7622598011
            ],
            "rsquared":0.0200084969,
            "aic":10.6933404719,
            "bic":10.58516077
        },
        "random_effects":{
            "coef":[
                -3.2581946582,
                -0.1830433381,
                1.0
            ],
            "pvalues":[
                1.206582769e-49,
                0.407753759,
                null
            ],
            "group_variance":0.082269653,
            "log_likelihood":-3.2866658734
        }
    },
    {
        "variable":"hbv",
        "studies involved":[
            "Alfano2018",
            "Gathogo2017",
            "Mazuecos2011",
            "Mazuecos2013",
            "Muller2015",
            "Roland2008",
            "Stock2010"
        ],
        "studies_details":[
            {
                "study_id":"Alfano2018",
                "fixed_effect":{
                    "coef":-4.0410569016,
                    "weight":0.513117284,
                    "ci_lower":-10.0845065344,
                    "ci_upper":2.0023927313
                },
                "random_effect":{
                    "coef":-3.5926361061,
                    "weight":0.513117284,
                    "ci_lower":-8.5368401448,
                    "ci_upper":1.3515679325
                }
            },
            {
                "study_id":"Gathogo2017",
                "fixed_effect":{
                    "coef":-4.0410569016,
                    "weight":1.0802469136,
                    "ci_lower":-10.0845065344,
                    "ci_upper":2.0023927313
                },
                "random_effect":{
                    "coef":-3.5926361061,
                    "weight":1.0802469136,
                    "ci_lower":-8.5368401448,
                    "ci_upper":1.3515679325
                }
            },
            {
                "study_id":"Mazuecos2011",
                "fixed_effect":{
                    "coef":-4.0410569016,
                    "weight":1.2014198692,
                    "ci_lower":-10.0845065344,
                    "ci_upper":2.0023927313
                },
                "random_effect":{
                    "coef":-3.5926361061,
                    "weight":1.2014198692,
                    "ci_lower":-8.5368401448,
                    "ci_upper":1.3515679325
                }
            },
            {
                "study_id":"Mazuecos2013",
                "fixed_effect":{
                    "coef":-4.0410569016,
                    "weight":1.0413028824,
                    "ci_lower":-10.0845065344,
                    "ci_upper":2.0023927313
                },
                "random_effect":{
                    "coef":-3.5926361061,
                    "weight":1.0413028824,
                    "ci_lower":-8.5368401448,
                    "ci_upper":1.3515679325
                }
            },
            {
                "study_id":"Muller2015",
                "fixed_effect":{
                    "coef":-4.0410569016,
                    "weight":0.7291666667,
                    "ci_lower":-10.0845065344,
                    "ci_upper":2.0023927313
                },
                "random_effect":{
                    "coef":-3.5926361061,
                    "weight":0.7291666667,
                    "ci_lower":-8.5368401448,
                    "ci_upper":1.3515679325
                }
            },
            {
                "study_id":"Roland2008",
                "fixed_effect":{
                    "coef":-4.0410569016,
                    "weight":0.4861111111,
                    "ci_lower":-10.0845065344,
                    "ci_upper":2.0023927313
                },
                "random_effect":{
                    "coef":-3.5926361061,
                    "weight":0.4861111111,
                    "ci_lower":-8.5368401448,
                    "ci_upper":1.3515679325
                }
            },
            {
                "study_id":"Stock2010",
                "fixed_effect":{
                    "coef":-4.0410569016,
                    "weight":4.0509259259,
                    "ci_lower":-10.0845065344,
                    "ci_upper":2.0023927313
                },
                "random_effect":{
                    "coef":-3.5926361061,
                    "weight":4.0509259259,
                    "ci_lower":-8.5368401448,
                    "ci_upper":1.3515679325
                }
            }
        ],
        "fixed_effects":{
            "coef":[
                -3.237878122,
                -4.0410569016
            ],
            "pvalues":[
                0.0000115347,
                0.2469654411
            ],
            "rsquared":0.2556910371,
            "aic":6.5066149786,
            "bic":6.3984352767
        },
        "random_effects":{
            "coef":[
                -3.2118325569,
                -3.5926361061,
                1.0
            ],
            "pvalues":[
                2.404912476e-137,
                0.1543867484,
                null
            ],
            "group_variance":0.0461009354,
            "log_likelihood":0.0204233624
        }
    },
    {
        "variable":"cd4",
        "studies involved":[
            "Alfano2018",
            "Mazuecos2013",
            "Muller2015",
            "Roland2008",
            "Stock2010"
        ],
        "studies_details":[
            {
                "study_id":"Alfano2018",
                "fixed_effect":{
                    "coef":-0.0000887548,
                    "weight":0.513117284,
                    "ci_lower":-0.0004574626,
                    "ci_upper":0.0002799529
                },
                "random_effect":{
                    "coef":0.000011177,
                    "weight":0.513117284,
                    "ci_lower":-0.0000386081,
                    "ci_upper":0.0000609622
                }
            },
            {
                "study_id":"Mazuecos2013",
                "fixed_effect":{
                    "coef":-0.0000887548,
                    "weight":1.0413028824,
                    "ci_lower":-0.0004574626,
                    "ci_upper":0.0002799529
                },
                "random_effect":{
                    "coef":0.000011177,
                    "weight":1.0413028824,
                    "ci_lower":-0.0000386081,
                    "ci_upper":0.0000609622
                }
            },
            {
                "study_id":"Muller2015",
                "fixed_effect":{
                    "coef":-0.0000887548,
                    "weight":0.7291666667,
                    "ci_lower":-0.0004574626,
                    "ci_upper":0.0002799529
                },
                "random_effect":{
                    "coef":0.000011177,
                    "weight":0.7291666667,
                    "ci_lower":-0.0000386081,
                    "ci_upper":0.0000609622
                }
            },
            {
                "study_id":"Roland2008",
                "fixed_effect":{
                    "coef":-0.0000887548,
                    "weight":0.4861111111,
                    "ci_lower":-0.0004574626,
                    "ci_upper":0.0002799529
                },
                "random_effect":{
                    "coef":0.000011177,
                    "weight":0.4861111111,
                    "ci_lower":-0.0000386081,
                    "ci_upper":0.0000609622
                }
            },
            {
                "study_id":"Stock2010",
                "fixed_effect":{
                    "coef":-0.0000887548,
                    "weight":4.0509259259,
                    "ci_lower":-0.0004574626,
                    "ci_upper":0.0002799529
                },
                "random_effect":{
                    "coef":0.000011177,
                    "weight":4.0509259259,
                    "ci_lower":-0.0000386081,
                    "ci_upper":0.0000609622
                }
            }
        ],
        "fixed_effects":{
            "coef":[
                -3.5026879573,
                -0.0000887548
            ],
            "pvalues":[
                0.0000363927,
                0.6692575985
            ],
            "rsquared":0.0690756117,
            "aic":-16.7720041951,
            "bic":-17.5531283703
        },
        "random_effects":{
            "coef":[
                -3.545425903,
                0.000011177,
                1.0
            ],
            "pvalues":[
                0.0,
                0.6599148514,
                null
            ],
            "group_variance":0.0007067604,
            "log_likelihood":-0.3508861628
        }
    },
    {
        "variable":"viral_suppress_pre",
        "studies involved":[
            "Alfano2018",
            "Gathogo2017",
            "Mazuecos2011",
            "Mazuecos2013",
            "Muller2015",
            "Roland2008",
            "Stock2010"
        ],
        "studies_details":[
            {
                "study_id":"Alfano2018",
                "fixed_effect":{
                    "coef":-4.2813759918,
                    "weight":0.513117284,
                    "ci_lower":-6.7105033461,
                    "ci_upper":-1.8522486375
                },
                "random_effect":{
                    "coef":-4.1455846502,
                    "weight":0.513117284,
                    "ci_lower":-4.3147922875,
                    "ci_upper":-3.9763770129
                }
            },
            {
                "study_id":"Gathogo2017",
                "fixed_effect":{
                    "coef":-4.2813759918,
                    "weight":1.0802469136,
                    "ci_lower":-6.7105033461,
                    "ci_upper":-1.8522486375
                },
                "random_effect":{
                    "coef":-4.1455846502,
                    "weight":1.0802469136,
                    "ci_lower":-4.3147922875,
                    "ci_upper":-3.9763770129
                }
            },
            {
                "study_id":"Mazuecos2011",
                "fixed_effect":{
                    "coef":-4.2813759918,
                    "weight":1.2014198692,
                    "ci_lower":-6.7105033461,
                    "ci_upper":-1.8522486375
                },
                "random_effect":{
                    "coef":-4.1455846502,
                    "weight":1.2014198692,
                    "ci_lower":-4.3147922875,
                    "ci_upper":-3.9763770129
                }
            },
            {
                "study_id":"Mazuecos2013",
                "fixed_effect":{
                    "coef":-4.2813759918,
                    "weight":1.0413028824,
                    "ci_lower":-6.7105033461,
                    "ci_upper":-1.8522486375
                },
                "random_effect":{
                    "coef":-4.1455846502,
                    "weight":1.0413028824,
                    "ci_lower":-4.3147922875,
                    "ci_upper":-3.9763770129
                }
            },
            {
                "study_id":"Muller2015",
                "fixed_effect":{
                    "coef":-4.2813759918,
                    "weight":0.7291666667,
                    "ci_lower":-6.7105033461,
                    "ci_upper":-1.8522486375
                },
                "random_effect":{
                    "coef":-4.1455846502,
                    "weight":0.7291666667,
                    "ci_lower":-4.3147922875,
                    "ci_upper":-3.9763770129
                }
            },
            {
                "study_id":"Roland2008",
                "fixed_effect":{
                    "coef":-4.2813759918,
                    "weight":0.4861111111,
                    "ci_lower":-6.7105033461,
                    "ci_upper":-1.8522486375
                },
                "random_effect":{
                    "coef":-4.1455846502,
                    "weight":0.4861111111,
                    "ci_lower":-4.3147922875,
                    "ci_upper":-3.9763770129
                }
            },
            {
                "study_id":"Stock2010",
                "fixed_effect":{
                    "coef":-4.2813759918,
                    "weight":4.0509259259,
                    "ci_lower":-6.7105033461,
                    "ci_upper":-1.8522486375
                },
                "random_effect":{
                    "coef":-4.1455846502,
                    "weight":4.0509259259,
                    "ci_lower":-4.3147922875,
                    "ci_upper":-3.9763770129
                }
            }
        ],
        "fixed_effects":{
            "coef":[
                0.7107727635,
                -4.2813759918
            ],
            "pvalues":[
                0.5797741549,
                0.0181488315
            ],
            "rsquared":0.7047323345,
            "aic":0.0345974273,
            "bic":-0.0735822746
        },
        "random_effects":{
            "coef":[
                0.5711204836,
                -4.1455846502,
                1.0
            ],
            "pvalues":[
                0.0,
                0.0,
                null
            ],
            "group_variance":0.0212319658,
            "log_likelihood":1.6724306346
        }
    },
    {
        "variable":"viral_suppress_post",
        "studies involved":[
            "Alfano2018",
            "Mazuecos2011",
            "Mazuecos2013",
            "Muller2015",
            "Roland2008",
            "Stock2010"
        ],
        "studies_details":[
            {
                "study_id":"Alfano2018",
                "fixed_effect":{
                    "coef":0.7285004971,
                    "weight":0.513117284,
                    "ci_lower":-1.2410448889,
                    "ci_upper":2.6980458831
                },
                "random_effect":{
                    "coef":0.2888851884,
                    "weight":0.513117284,
                    "ci_lower":0.0517694345,
                    "ci_upper":0.5260009424
                }
            },
            {
                "study_id":"Mazuecos2011",
                "fixed_effect":{
                    "coef":0.7285004971,
                    "weight":1.2014198692,
                    "ci_lower":-1.2410448889,
                    "ci_upper":2.6980458831
                },
                "random_effect":{
                    "coef":0.2888851884,
                    "weight":1.2014198692,
                    "ci_lower":0.0517694345,
                    "ci_upper":0.5260009424
                }
            },
            {
                "study_id":"Mazuecos2013",
                "fixed_effect":{
                    "coef":0.7285004971,
                    "weight":1.0413028824,
                    "ci_lower":-1.2410448889,
                    "ci_upper":2.6980458831
                },
                "random_effect":{
                    "coef":0.2888851884,
                    "weight":1.0413028824,
                    "ci_lower":0.0517694345,
                    "ci_upper":0.5260009424
                }
            },
            {
                "study_id":"Muller2015",
                "fixed_effect":{
                    "coef":0.7285004971,
                    "weight":0.7291666667,
                    "ci_lower":-1.2410448889,
                    "ci_upper":2.6980458831
                },
                "random_effect":{
                    "coef":0.2888851884,
                    "weight":0.7291666667,
                    "ci_lower":0.0517694345,
                    "ci_upper":0.5260009424
                }
            },
            {
                "study_id":"Roland2008",
                "fixed_effect":{
                    "coef":0.7285004971,
                    "weight":0.4861111111,
                    "ci_lower":-1.2410448889,
                    "ci_upper":2.6980458831
                },
                "random_effect":{
                    "coef":0.2888851884,
                    "weight":0.4861111111,
                    "ci_lower":0.0517694345,
                    "ci_upper":0.5260009424
                }
            },
            {
                "study_id":"Stock2010",
                "fixed_effect":{
                    "coef":0.7285004971,
                    "weight":4.0509259259,
                    "ci_lower":-1.2410448889,
                    "ci_upper":2.6980458831
                },
                "random_effect":{
                    "coef":0.2888851884,
                    "weight":4.0509259259,
                    "ci_lower":0.0517694345,
                    "ci_upper":0.5260009424
                }
            }
        ],
        "fixed_effects":{
            "coef":[
                -3.994804368,
                0.7285004971
            ],
            "pvalues":[
                0.0079744112,
                0.5086085647
            ],
            "rsquared":0.116135634,
            "aic":8.0371001444,
            "bic":7.6206190829
        },
        "random_effects":{
            "coef":[
                -3.6458422355,
                0.2888851884,
                1.0
            ],
            "pvalues":[
                0.0,
                0.0169437345,
                null
            ],
            "group_variance":0.0762536016,
            "log_likelihood":-1.8543883767
        }
    },
    {
        "variable":"atg",
        "studies involved":[
            "Locke2014",
            "Mazuecos2011",
            "Mazuecos2013",
            "Muller2015",
            "Stock2010",
            "Vicari2016"
        ],
        "studies_details":[
            {
                "study_id":"Locke2014",
                "fixed_effect":{
                    "coef":-1.1304427566,
                    "weight":12.5775,
                    "ci_lower":-2.8343581223,
                    "ci_upper":0.573472609
                },
                "random_effect":{
                    "coef":-0.7114277329,
                    "weight":12.5775,
                    "ci_lower":-1.4797422264,
                    "ci_upper":0.0568867607
                }
            },
            {
                "study_id":"Mazuecos2011",
                "fixed_effect":{
                    "coef":-1.1304427566,
                    "weight":1.2014198692,
                    "ci_lower":-2.8343581223,
                    "ci_upper":0.573472609
                },
                "random_effect":{
                    "coef":-0.7114277329,
                    "weight":1.2014198692,
                    "ci_lower":-1.4797422264,
                    "ci_upper":0.0568867607
                }
            },
            {
                "study_id":"Mazuecos2013",
                "fixed_effect":{
                    "coef":-1.1304427566,
                    "weight":1.0413028824,
                    "ci_lower":-2.8343581223,
                    "ci_upper":0.573472609
                },
                "random_effect":{
                    "coef":-0.7114277329,
                    "weight":1.0413028824,
                    "ci_lower":-1.4797422264,
                    "ci_upper":0.0568867607
                }
            },
            {
                "study_id":"Muller2015",
                "fixed_effect":{
                    "coef":-1.1304427566,
                    "weight":0.658125,
                    "ci_lower":-2.8343581223,
                    "ci_upper":0.573472609
                },
                "random_effect":{
                    "coef":-0.7114277329,
                    "weight":0.658125,
                    "ci_lower":-1.4797422264,
                    "ci_upper":0.0568867607
                }
            },
            {
                "study_id":"Stock2010",
                "fixed_effect":{
                    "coef":-1.1304427566,
                    "weight":3.65625,
                    "ci_lower":-2.8343581223,
                    "ci_upper":0.573472609
                },
                "random_effect":{
                    "coef":-0.7114277329,
                    "weight":3.65625,
                    "ci_lower":-1.4797422264,
                    "ci_upper":0.0568867607
                }
            },
            {
                "study_id":"Vicari2016",
                "fixed_effect":{
                    "coef":-1.1304427566,
                    "weight":2.6417621788,
                    "ci_lower":-2.8343581223,
                    "ci_upper":0.573472609
                },
                "random_effect":{
                    "coef":-0.7114277329,
                    "weight":2.6417621788,
                    "ci_lower":-1.4797422264,
                    "ci_upper":0.0568867607
                }
            }
        ],
        "fixed_effects":{
            "coef":[
                -3.2214474949,
                -1.1304427566
            ],
            "pvalues":[
                0.0002344991,
                0.2633462314
            ],
            "rsquared":0.2971212325,
            "aic":8.3961025882,
            "bic":7.9796215267
        },
        "random_effects":{
            "coef":[
                -3.1231865175,
                -0.7114277329,
                1.0
            ],
            "pvalues":[
                5.769478689e-44,
                0.069542403,
                null
            ],
            "group_variance":0.0815392283,
            "log_likelihood":-2.7155112239
        }
    },
    {
        "variable":"il_2",
        "studies involved":[
            "Alfano2018",
            "Locke2014",
            "Mazuecos2011",
            "Mazuecos2013",
            "Roland2008",
            "Stock2010",
            "Vicari2016"
        ],
        "studies_details":[
            {
                "study_id":"Alfano2018",
                "fixed_effect":{
                    "coef":-0.1423026972,
                    "weight":0.513117284,
                    "ci_lower":-2.2302732949,
                    "ci_upper":1.9456679006
                },
                "random_effect":{
                    "coef":-0.5150891621,
                    "weight":0.513117284,
                    "ci_lower":-1.3968705133,
                    "ci_upper":0.3666921891
                }
            },
            {
                "study_id":"Locke2014",
                "fixed_effect":{
                    "coef":-0.1423026972,
                    "weight":13.9351851852,
                    "ci_lower":-2.2302732949,
                    "ci_upper":1.9456679006
                },
                "random_effect":{
                    "coef":-0.5150891621,
                    "weight":13.9351851852,
                    "ci_lower":-1.3968705133,
                    "ci_upper":0.3666921891
                }
            },
            {
                "study_id":"Mazuecos2011",
                "fixed_effect":{
                    "coef":-0.1423026972,
                    "weight":1.2014198692,
                    "ci_lower":-2.2302732949,
                    "ci_upper":1.9456679006
                },
                "random_effect":{
                    "coef":-0.5150891621,
                    "weight":1.2014198692,
                    "ci_lower":-1.3968705133,
                    "ci_upper":0.3666921891
                }
            },
            {
                "study_id":"Mazuecos2013",
                "fixed_effect":{
                    "coef":-0.1423026972,
                    "weight":1.0413028824,
                    "ci_lower":-2.2302732949,
                    "ci_upper":1.9456679006
                },
                "random_effect":{
                    "coef":-0.5150891621,
                    "weight":1.0413028824,
                    "ci_lower":-1.3968705133,
                    "ci_upper":0.3666921891
                }
            },
            {
                "study_id":"Roland2008",
                "fixed_effect":{
                    "coef":-0.1423026972,
                    "weight":0.4861111111,
                    "ci_lower":-2.2302732949,
                    "ci_upper":1.9456679006
                },
                "random_effect":{
                    "coef":-0.5150891621,
                    "weight":0.4861111111,
                    "ci_lower":-1.3968705133,
                    "ci_upper":0.3666921891
                }
            },
            {
                "study_id":"Stock2010",
                "fixed_effect":{
                    "coef":-0.1423026972,
                    "weight":4.0509259259,
                    "ci_lower":-2.2302732949,
                    "ci_upper":1.9456679006
                },
                "random_effect":{
                    "coef":-0.5150891621,
                    "weight":4.0509259259,
                    "ci_lower":-1.3968705133,
                    "ci_upper":0.3666921891
                }
            },
            {
                "study_id":"Vicari2016",
                "fixed_effect":{
                    "coef":-0.1423026972,
                    "weight":2.6417621788,
                    "ci_lower":-2.2302732949,
                    "ci_upper":1.9456679006
                },
                "random_effect":{
                    "coef":-0.5150891621,
                    "weight":2.6417621788,
                    "ci_lower":-1.3968705133,
                    "ci_upper":0.3666921891
                }
            }
        ],
        "fixed_effects":{
            "coef":[
                -3.3797003415,
                -0.1423026972
            ],
            "pvalues":[
                0.0005232624,
                0.8989438759
            ],
            "rsquared":0.003556088,
            "aic":10.2779254133,
            "bic":10.1697457114
        },
        "random_effects":{
            "coef":[
                -3.0856476314,
                -0.5150891621,
                1.0
            ],
            "pvalues":[
                3.000290672e-188,
                0.2522396424,
                null
            ],
            "group_variance":0.0745191975,
            "log_likelihood":-2.805921581
        }
    },
    {
        "variable":"induction_use",
        "studies involved":[
            "Alfano2018",
            "Locke2014",
            "Mazuecos2013",
            "Muller2015",
            "Roland2008",
            "Stock2010",
            "Vicari2016"
        ],
        "studies_details":[
            {
                "study_id":"Alfano2018",
                "fixed_effect":{
                    "coef":-0.7136343804,
                    "weight":0.513117284,
                    "ci_lower":-1.9458822537,
                    "ci_upper":0.5186134929
                },
                "random_effect":{
                    "coef":-0.3308814624,
                    "weight":0.513117284,
                    "ci_lower":-1.110243489,
                    "ci_upper":0.4484805643
                }
            },
            {
                "study_id":"Locke2014",
                "fixed_effect":{
                    "coef":-0.7136343804,
                    "weight":13.9351851852,
                    "ci_lower":-1.9458822537,
                    "ci_upper":0.5186134929
                },
                "random_effect":{
                    "coef":-0.3308814624,
                    "weight":13.9351851852,
                    "ci_lower":-1.110243489,
                    "ci_upper":0.4484805643
                }
            },
            {
                "study_id":"Mazuecos2013",
                "fixed_effect":{
                    "coef":-0.7136343804,
                    "weight":1.0413028824,
                    "ci_lower":-1.9458822537,
                    "ci_upper":0.5186134929
                },
                "random_effect":{
                    "coef":-0.3308814624,
                    "weight":1.0413028824,
                    "ci_lower":-1.110243489,
                    "ci_upper":0.4484805643
                }
            },
            {
                "study_id":"Muller2015",
                "fixed_effect":{
                    "coef":-0.7136343804,
                    "weight":0.7291666667,
                    "ci_lower":-1.9458822537,
                    "ci_upper":0.5186134929
                },
                "random_effect":{
                    "coef":-0.3308814624,
                    "weight":0.7291666667,
                    "ci_lower":-1.110243489,
                    "ci_upper":0.4484805643
                }
            },
            {
                "study_id":"Roland2008",
                "fixed_effect":{
                    "coef":-0.7136343804,
                    "weight":0.4861111111,
                    "ci_lower":-1.9458822537,
                    "ci_upper":0.5186134929
                },
                "random_effect":{
                    "coef":-0.3308814624,
                    "weight":0.4861111111,
                    "ci_lower":-1.110243489,
                    "ci_upper":0.4484805643
                }
            },
            {
                "study_id":"Stock2010",
                "fixed_effect":{
                    "coef":-0.7136343804,
                    "weight":4.0509259259,
                    "ci_lower":-1.9458822537,
                    "ci_upper":0.5186134929
                },
                "random_effect":{
                    "coef":-0.3308814624,
                    "weight":4.0509259259,
                    "ci_lower":-1.110243489,
                    "ci_upper":0.4484805643
                }
            },
            {
                "study_id":"Vicari2016",
                "fixed_effect":{
                    "coef":-0.7136343804,
                    "weight":2.6417621788,
                    "ci_lower":-1.9458822537,
                    "ci_upper":0.5186134929
                },
                "random_effect":{
                    "coef":-0.3308814624,
                    "weight":2.6417621788,
                    "ci_lower":-1.110243489,
                    "ci_upper":0.4484805643
                }
            }
        ],
        "fixed_effects":{
            "coef":[
                -3.001149776,
                -0.7136343804
            ],
            "pvalues":[
                0.0009049772,
                0.307799718
            ],
            "rsquared":0.2048914878,
            "aic":5.4980054687,
            "bic":5.3898257668
        },
        "random_effects":{
            "coef":[
                -3.2235519421,
                -0.3308814624,
                1.0
            ],
            "pvalues":[
                5.892660536e-29,
                0.4053376389,
                null
            ],
            "group_variance":0.0324384299,
            "log_likelihood":-0.7840790105
        }
    },
    {
        "variable":"ii_pre",
        "studies involved":[
            "Alfano2018",
            "Roland2008"
        ],
        "studies_details":[
            {
                "study_id":"Alfano2018",
                "fixed_effect":{
                    "coef":-9.515194089e-16,
                    "weight":0.513117284,
                    "ci_lower":null,
                    "ci_upper":null
                },
                "random_effect":{
                    "coef":0.0,
                    "weight":0.513117284,
                    "ci_lower":null,
                    "ci_upper":null
                }
            },
            {
                "study_id":"Roland2008",
                "fixed_effect":{
                    "coef":-9.515194089e-16,
                    "weight":0.4861111111,
                    "ci_lower":null,
                    "ci_upper":null
                },
                "random_effect":{
                    "coef":0.0,
                    "weight":0.4861111111,
                    "ci_lower":null,
                    "ci_upper":null
                }
            }
        ],
        "fixed_effects":{
            "coef":[
                -3.5553480615,
                -9.515194089e-16
            ],
            "pvalues":[
                null,
                null
            ],
            "rsquared":-4.0038610039,
            "aic":-128.5051203439,
            "bic":-131.1188259828
        },
        "random_effects":{
            "coef":[
                -3.5553480615,
                0.0,
                1.0
            ],
            "pvalues":[
                null,
                null,
                null
            ],
            "group_variance":null,
            "log_likelihood":null
        }
    },
    {
        "variable":"ii_post",
        "studies involved":[
            "Alfano2018",
            "Roland2008"
        ],
        "studies_details":[
            {
                "study_id":"Alfano2018",
                "fixed_effect":{
                    "coef":-0.0,
                    "weight":0.513117284,
                    "ci_lower":null,
                    "ci_upper":null
                },
                "random_effect":{
                    "coef":0.0,
                    "weight":0.513117284,
                    "ci_lower":null,
                    "ci_upper":null
                }
            },
            {
                "study_id":"Roland2008",
                "fixed_effect":{
                    "coef":-0.0,
                    "weight":0.4861111111,
                    "ci_lower":null,
                    "ci_upper":null
                },
                "random_effect":{
                    "coef":0.0,
                    "weight":0.4861111111,
                    "ci_lower":null,
                    "ci_upper":null
                }
            }
        ],
        "fixed_effects":{
            "coef":[
                -3.5553480615,
                -0.0
            ],
            "pvalues":[
                null,
                null
            ],
            "rsquared":-1.0015444015,
            "aic":-130.3377018076,
            "bic":-132.9514074465
        },
        "random_effects":{
            "coef":[
                -3.5553480615,
                0.0,
                1.0
            ],
            "pvalues":[
                null,
                null,
                null
            ],
            "group_variance":null,
            "log_likelihood":null
        }
    },
    {
        "variable":"pi_pre",
        "studies involved":[
            "Alfano2018",
            "Muller2015",
            "Roland2008",
            "Stock2010",
            "Vicari2016"
        ],
        "studies_details":[
            {
                "study_id":"Alfano2018",
                "fixed_effect":{
                    "coef":-1.4230851485,
                    "weight":0.513117284,
                    "ci_lower":-5.548915776,
                    "ci_upper":2.702745479
                },
                "random_effect":{
                    "coef":-0.9937001243,
                    "weight":0.513117284,
                    "ci_lower":-1.2681021054,
                    "ci_upper":-0.7192981433
                }
            },
            {
                "study_id":"Muller2015",
                "fixed_effect":{
                    "coef":-1.4230851485,
                    "weight":0.7291666667,
                    "ci_lower":-5.548915776,
                    "ci_upper":2.702745479
                },
                "random_effect":{
                    "coef":-0.9937001243,
                    "weight":0.7291666667,
                    "ci_lower":-1.2681021054,
                    "ci_upper":-0.7192981433
                }
            },
            {
                "study_id":"Roland2008",
                "fixed_effect":{
                    "coef":-1.4230851485,
                    "weight":0.4861111111,
                    "ci_lower":-5.548915776,
                    "ci_upper":2.702745479
                },
                "random_effect":{
                    "coef":-0.9937001243,
                    "weight":0.4861111111,
                    "ci_lower":-1.2681021054,
                    "ci_upper":-0.7192981433
                }
            },
            {
                "study_id":"Stock2010",
                "fixed_effect":{
                    "coef":-1.4230851485,
                    "weight":4.0509259259,
                    "ci_lower":-5.548915776,
                    "ci_upper":2.702745479
                },
                "random_effect":{
                    "coef":-0.9937001243,
                    "weight":4.0509259259,
                    "ci_lower":-1.2681021054,
                    "ci_upper":-0.7192981433
                }
            },
            {
                "study_id":"Vicari2016",
                "fixed_effect":{
                    "coef":-1.4230851485,
                    "weight":2.6417621788,
                    "ci_lower":-5.548915776,
                    "ci_upper":2.702745479
                },
                "random_effect":{
                    "coef":-0.9937001243,
                    "weight":2.6417621788,
                    "ci_lower":-1.2681021054,
                    "ci_upper":-0.7192981433
                }
            }
        ],
        "fixed_effects":{
            "coef":[
                -2.7227327232,
                -1.4230851485
            ],
            "pvalues":[
                0.0623622753,
                0.5474636256
            ],
            "rsquared":0.1322047709,
            "aic":7.6564512826,
            "bic":6.8753271075
        },
        "random_effects":{
            "coef":[
                -2.9218224447,
                -0.9937001243,
                1.0
            ],
            "pvalues":[
                0.0,
                0.0,
                null
            ],
            "group_variance":0.0470507108,
            "log_likelihood":-0.2005736695
        }
    },
    {
        "variable":"pi_post",
        "studies involved":[
            "Alfano2018",
            "Muller2015",
            "Roland2008",
            "Stock2010",
            "Vicari2016"
        ],
        "studies_details":[
            {
                "study_id":"Alfano2018",
                "fixed_effect":{
                    "coef":-0.5785636391,
                    "weight":0.513117284,
                    "ci_lower":-5.5369937755,
                    "ci_upper":4.3798664974
                },
                "random_effect":{
                    "coef":-0.1059604381,
                    "weight":0.513117284,
                    "ci_lower":-0.1059604381,
                    "ci_upper":-0.1059604381
                }
            },
            {
                "study_id":"Muller2015",
                "fixed_effect":{
                    "coef":-0.5785636391,
                    "weight":0.7291666667,
                    "ci_lower":-5.5369937755,
                    "ci_upper":4.3798664974
                },
                "random_effect":{
                    "coef":-0.1059604381,
                    "weight":0.7291666667,
                    "ci_lower":-0.1059604381,
                    "ci_upper":-0.1059604381
                }
            },
            {
                "study_id":"Roland2008",
                "fixed_effect":{
                    "coef":-0.5785636391,
                    "weight":0.4861111111,
                    "ci_lower":-5.5369937755,
                    "ci_upper":4.3798664974
                },
                "random_effect":{
                    "coef":-0.1059604381,
                    "weight":0.4861111111,
                    "ci_lower":-0.1059604381,
                    "ci_upper":-0.1059604381
                }
            },
            {
                "study_id":"Stock2010",
                "fixed_effect":{
                    "coef":-0.5785636391,
                    "weight":4.0509259259,
                    "ci_lower":-5.5369937755,
                    "ci_upper":4.3798664974
                },
                "random_effect":{
                    "coef":-0.1059604381,
                    "weight":4.0509259259,
                    "ci_lower":-0.1059604381,
                    "ci_upper":-0.1059604381
                }
            },
            {
                "study_id":"Vicari2016",
                "fixed_effect":{
                    "coef":-0.5785636391,
                    "weight":2.6417621788,
                    "ci_lower":-5.5369937755,
                    "ci_upper":4.3798664974
                },
                "random_effect":{
                    "coef":-0.1059604381,
                    "weight":2.6417621788,
                    "ci_lower":-0.1059604381,
                    "ci_upper":-0.1059604381
                }
            }
        ],
        "fixed_effects":{
            "coef":[
                -3.109816064,
                -0.5785636391
            ],
            "pvalues":[
                0.059650985,
                0.8338065107
            ],
            "rsquared":0.0171355633,
            "aic":8.2790284191,
            "bic":7.497904244
        },
        "random_effects":{
            "coef":[
                -3.3790866358,
                -0.1059604381,
                1.0
            ],
            "pvalues":[
                1.081296516e-107,
                0.0,
                null
            ],
            "group_variance":0.0587411605,
            "log_likelihood":-0.5897958433
        }
    },
    {
        "variable":"nrti_pre",
        "studies involved":[
            "Alfano2018",
            "Roland2008",
            "Stock2010",
            "Vicari2016"
        ],
        "studies_details":[
            {
                "study_id":"Alfano2018",
                "fixed_effect":{
                    "coef":0.5479228235,
                    "weight":0.513117284,
                    "ci_lower":0.0045149488,
                    "ci_upper":1.0913306982
                },
                "random_effect":{
                    "coef":0.3266312382,
                    "weight":0.513117284,
                    "ci_lower":0.0495104253,
                    "ci_upper":0.6037520511
                }
            },
            {
                "study_id":"Roland2008",
                "fixed_effect":{
                    "coef":0.5479228235,
                    "weight":0.4861111111,
                    "ci_lower":0.0045149488,
                    "ci_upper":1.0913306982
                },
                "random_effect":{
                    "coef":0.3266312382,
                    "weight":0.4861111111,
                    "ci_lower":0.0495104253,
                    "ci_upper":0.6037520511
                }
            },
            {
                "study_id":"Stock2010",
                "fixed_effect":{
                    "coef":0.5479228235,
                    "weight":4.0509259259,
                    "ci_lower":0.0045149488,
                    "ci_upper":1.0913306982
                },
                "random_effect":{
                    "coef":0.3266312382,
                    "weight":4.0509259259,
                    "ci_lower":0.0495104253,
                    "ci_upper":0.6037520511
                }
            },
            {
                "study_id":"Vicari2016",
                "fixed_effect":{
                    "coef":0.5479228235,
                    "weight":2.6417621788,
                    "ci_lower":0.0045149488,
                    "ci_upper":1.0913306982
                },
                "random_effect":{
                    "coef":0.3266312382,
                    "weight":2.6417621788,
                    "ci_lower":0.0495104253,
                    "ci_upper":0.6037520511
                }
            }
        ],
        "fixed_effects":{
            "coef":[
                -3.5864442407,
                0.5479228235
            ],
            "pvalues":[
                0.0026395312,
                0.1867692688
            ],
            "rsquared":0.6613442222,
            "aic":3.4276063289,
            "bic":2.2001950512
        },
        "random_effects":{
            "coef":[
                -3.6153991496,
                0.3266312382,
                1.0
            ],
            "pvalues":[
                0.0,
                0.0208785369,
                null
            ],
            "group_variance":0.0661301588,
            "log_likelihood":-1.2735346927
        }
    },
    {
        "variable":"nrti_post",
        "studies involved":[
            "Alfano2018",
            "Roland2008",
            "Stock2010",
            "Vicari2016"
        ],
        "studies_details":[
            {
                "study_id":"Alfano2018",
                "fixed_effect":{
                    "coef":0.5479228235,
                    "weight":0.513117284,
                    "ci_lower":0.0045149488,
                    "ci_upper":1.0913306982
                },
                "random_effect":{
                    "coef":0.3266312382,
                    "weight":0.513117284,
                    "ci_lower":0.0495104253,
                    "ci_upper":0.6037520511
                }
            },
            {
                "study_id":"Roland2008",
                "fixed_effect":{
                    "coef":0.5479228235,
                    "weight":0.4861111111,
                    "ci_lower":0.0045149488,
                    "ci_upper":1.0913306982
                },
                "random_effect":{
                    "coef":0.3266312382,
                    "weight":0.4861111111,
                    "ci_lower":0.0495104253,
                    "ci_upper":0.6037520511
                }
            },
            {
                "study_id":"Stock2010",
                "fixed_effect":{
                    "coef":0.5479228235,
                    "weight":4.0509259259,
                    "ci_lower":0.0045149488,
                    "ci_upper":1.0913306982
                },
                "random_effect":{
                    "coef":0.3266312382,
                    "weight":4.0509259259,
                    "ci_lower":0.0495104253,
                    "ci_upper":0.6037520511
                }
            },
            {
                "study_id":"Vicari2016",
                "fixed_effect":{
                    "coef":0.5479228235,
                    "weight":2.6417621788,
                    "ci_lower":0.0045149488,
                    "ci_upper":1.0913306982
                },
                "random_effect":{
                    "coef":0.3266312382,
                    "weight":2.6417621788,
                    "ci_lower":0.0495104253,
                    "ci_upper":0.6037520511
                }
            }
        ],
        "fixed_effects":{
            "coef":[
                -3.5864442407,
                0.5479228235
            ],
            "pvalues":[
                0.0026395312,
                0.1867692688
            ],
            "rsquared":0.6613442222,
            "aic":3.4276063289,
            "bic":2.2001950512
        },
        "random_effects":{
            "coef":[
                -3.6153991496,
                0.3266312382,
                1.0
            ],
            "pvalues":[
                0.0,
                0.0208785369,
                null
            ],
            "group_variance":0.0661301588,
            "log_likelihood":-1.2735346927
        }
    },
    {
        "variable":"nnrti_pre",
        "studies involved":[
            "Alfano2018",
            "Muller2015",
            "Roland2008",
            "Stock2010",
            "Vicari2016"
        ],
        "studies_details":[
            {
                "study_id":"Alfano2018",
                "fixed_effect":{
                    "coef":1.6084177817,
                    "weight":0.513117284,
                    "ci_lower":-0.9900241027,
                    "ci_upper":4.206859666
                },
                "random_effect":{
                    "coef":0.5024427847,
                    "weight":0.513117284,
                    "ci_lower":0.1483106611,
                    "ci_upper":0.8565749083
                }
            },
            {
                "study_id":"Muller2015",
                "fixed_effect":{
                    "coef":1.6084177817,
                    "weight":0.7291666667,
                    "ci_lower":-0.9900241027,
                    "ci_upper":4.206859666
                },
                "random_effect":{
                    "coef":0.5024427847,
                    "weight":0.7291666667,
                    "ci_lower":0.1483106611,
                    "ci_upper":0.8565749083
                }
            },
            {
                "study_id":"Roland2008",
                "fixed_effect":{
                    "coef":1.6084177817,
                    "weight":0.4861111111,
                    "ci_lower":-0.9900241027,
                    "ci_upper":4.206859666
                },
                "random_effect":{
                    "coef":0.5024427847,
                    "weight":0.4861111111,
                    "ci_lower":0.1483106611,
                    "ci_upper":0.8565749083
                }
            },
            {
                "study_id":"Stock2010",
                "fixed_effect":{
                    "coef":1.6084177817,
                    "weight":4.0509259259,
                    "ci_lower":-0.9900241027,
                    "ci_upper":4.206859666
                },
                "random_effect":{
                    "coef":0.5024427847,
                    "weight":4.0509259259,
                    "ci_lower":0.1483106611,
                    "ci_upper":0.8565749083
                }
            },
            {
                "study_id":"Vicari2016",
                "fixed_effect":{
                    "coef":1.6084177817,
                    "weight":2.6417621788,
                    "ci_lower":-0.9900241027,
                    "ci_upper":4.206859666
                },
                "random_effect":{
                    "coef":0.5024427847,
                    "weight":2.6417621788,
                    "ci_lower":0.1483106611,
                    "ci_upper":0.8565749083
                }
            }
        ],
        "fixed_effects":{
            "coef":[
                -4.0768584423,
                1.6084177817
            ],
            "pvalues":[
                0.0071266658,
                0.3118548461
            ],
            "rsquared":0.3291470349,
            "aic":6.3694223292,
            "bic":5.5882981541
        },
        "random_effects":{
            "coef":[
                -3.6481862854,
                0.5024427847,
                1.0
            ],
            "pvalues":[
                0.0,
                0.0054216998,
                null
            ],
            "group_variance":0.0534444824,
            "log_likelihood":-0.6854304062
        }
    },
    {
        "variable":"nnrti_post",
        "studies involved":[
            "Alfano2018",
            "Roland2008",
            "Stock2010",
            "Vicari2016"
        ],
        "studies_details":[
            {
                "study_id":"Alfano2018",
                "fixed_effect":{
                    "coef":2.4597849459,
                    "weight":0.513117284,
                    "ci_lower":-0.6807081109,
                    "ci_upper":5.6002780027
                },
                "random_effect":{
                    "coef":0.8459526145,
                    "weight":0.513117284,
                    "ci_lower":0.4741403843,
                    "ci_upper":1.2177648447
                }
            },
            {
                "study_id":"Roland2008",
                "fixed_effect":{
                    "coef":2.4597849459,
                    "weight":0.4861111111,
                    "ci_lower":-0.6807081109,
                    "ci_upper":5.6002780027
                },
                "random_effect":{
                    "coef":0.8459526145,
                    "weight":0.4861111111,
                    "ci_lower":0.4741403843,
                    "ci_upper":1.2177648447
                }
            },
            {
                "study_id":"Stock2010",
                "fixed_effect":{
                    "coef":2.4597849459,
                    "weight":4.0509259259,
                    "ci_lower":-0.6807081109,
                    "ci_upper":5.6002780027
                },
                "random_effect":{
                    "coef":0.8459526145,
                    "weight":4.0509259259,
                    "ci_lower":0.4741403843,
                    "ci_upper":1.2177648447
                }
            },
            {
                "study_id":"Vicari2016",
                "fixed_effect":{
                    "coef":2.4597849459,
                    "weight":2.6417621788,
                    "ci_lower":-0.6807081109,
                    "ci_upper":5.6002780027
                },
                "random_effect":{
                    "coef":0.8459526145,
                    "weight":2.6417621788,
                    "ci_lower":0.4741403843,
                    "ci_upper":1.2177648447
                }
            }
        ],
        "fixed_effects":{
            "coef":[
                -4.4370530451,
                2.4597849459
            ],
            "pvalues":[
                0.0266128074,
                0.2645133363
            ],
            "rsquared":0.5409406324,
            "aic":4.6443877529,
            "bic":3.4169764752
        },
        "random_effects":{
            "coef":[
                -3.7730075525,
                0.8459526145,
                1.0
            ],
            "pvalues":[
                0.0,
                0.0000082182,
                null
            ],
            "group_variance":0.0696748476,
            "log_likelihood":-0.2547172405
        }
    }
]