[
    {
        "studies_involved":[
            "Azar2017",
            "Camargo2019",
            "Durand2021",
            "Muller2015",
            "Muthukumar2013",
            "Stock2010",
            "Touzot2010"
        ],
        "factors":[
            "pi_avoid",
            "atg",
            "cd4"
        ],
        "fixed_effects":{
            "coef":[
                0.7569667038,
                0.5325131587,
                -0.3055455451,
                0.0043127287
            ],
            "upper_ci":[
                1.9891804443,
                0.9159419668,
                0.3230034596,
                0.0063956293
            ],
            "lower_ci":[
                -0.4752470366,
                0.1490843507,
                -0.9340945499,
                0.0022298281
            ],
            "pvalues":[
                0.3149037831,
                0.0724219577,
                0.4109917794,
                0.026966458
            ],
            "rsquared":0.9479733695,
            "aic":1.3704185401,
            "bic":1.1540591363
        },
        "random_effects":{
            "coef":[
                0.9350712717,
                0.3700736559,
                -0.2647771216,
                0.0040983916,
                1.0
            ],
            "upper_ci":[
                1.9939302407,
                0.8407145704,
                0.0380712808,
                0.0063736435,
                null
            ],
            "lower_ci":[
                -0.1237876973,
                -0.1005672587,
                -0.5676255241,
                0.0018231398,
                null
            ],
            "pvalues":[
                0.0834762223,
                0.1232719493,
                0.0866009173,
                0.0004147262,
                null
            ],
            "group_variance":0.0485221027,
            "log_likelihood":-7.2695171902
        }
    }
]