[
    {
        "variable":"hivan",
        "studies involved":[
            "Ailioaie2017",
            "Alfano2018",
            "Gathogo2017",
            "Izzo2018",
            "Muller2015",
            "Roland2016"
        ],
        "studies_details":[
            {
                "study_id":"Ailioaie2017",
                "fixed_effect":{
                    "coef":1.80522368,
                    "weight":2.625,
                    "ci_lower":0.8495784049,
                    "ci_upper":2.7608689551
                },
                "random_effect":{
                    "coef":1.9760388373,
                    "weight":2.625,
                    "ci_lower":1.4355804896,
                    "ci_upper":2.5164971851
                }
            },
            {
                "study_id":"Alfano2018",
                "fixed_effect":{
                    "coef":1.80522368,
                    "weight":4.634404,
                    "ci_lower":0.8495784049,
                    "ci_upper":2.7608689551
                },
                "random_effect":{
                    "coef":1.9760388373,
                    "weight":4.634404,
                    "ci_lower":1.4355804896,
                    "ci_upper":2.5164971851
                }
            },
            {
                "study_id":"Gathogo2017",
                "fixed_effect":{
                    "coef":1.80522368,
                    "weight":6.864,
                    "ci_lower":0.8495784049,
                    "ci_upper":2.7608689551
                },
                "random_effect":{
                    "coef":1.9760388373,
                    "weight":6.864,
                    "ci_lower":1.4355804896,
                    "ci_upper":2.5164971851
                }
            },
            {
                "study_id":"Izzo2018",
                "fixed_effect":{
                    "coef":1.80522368,
                    "weight":5.717712,
                    "ci_lower":0.8495784049,
                    "ci_upper":2.7608689551
                },
                "random_effect":{
                    "coef":1.9760388373,
                    "weight":5.717712,
                    "ci_lower":1.4355804896,
                    "ci_upper":2.5164971851
                }
            },
            {
                "study_id":"Muller2015",
                "fixed_effect":{
                    "coef":1.80522368,
                    "weight":3.6288,
                    "ci_lower":0.8495784049,
                    "ci_upper":2.7608689551
                },
                "random_effect":{
                    "coef":1.9760388373,
                    "weight":3.6288,
                    "ci_lower":1.4355804896,
                    "ci_upper":2.5164971851
                }
            },
            {
                "study_id":"Roland2016",
                "fixed_effect":{
                    "coef":1.80522368,
                    "weight":31.91265,
                    "ci_lower":0.8495784049,
                    "ci_upper":2.7608689551
                },
                "random_effect":{
                    "coef":1.9760388373,
                    "weight":31.91265,
                    "ci_lower":1.4355804896,
                    "ci_upper":2.5164971851
                }
            }
        ],
        "fixed_effects":{
            "coef":[
                0.3830159171,
                1.80522368
            ],
            "pvalues":[
                0.0951678333,
                0.0207906303
            ],
            "rsquared":0.7741160752,
            "aic":2.5785683514,
            "bic":2.1620872898
        },
        "random_effects":{
            "coef":[
                0.3636121186,
                1.9760388373,
                1.0
            ],
            "pvalues":[
                0.1200919359,
                0.0,
                null
            ],
            "group_variance":0.0587084155,
            "log_likelihood":-1.738227335
        }
    },
    {
        "variable":"hcv",
        "studies involved":[
            "Ailioaie2017",
            "Alfano2018",
            "Alfano2020",
            "Gathogo2017",
            "Izzo2018",
            "Locke2015",
            "Mazuecos2011",
            "Mazuecos2012",
            "Qiu2006",
            "Roland2016"
        ],
        "studies_details":[
            {
                "study_id":"Ailioaie2017",
                "fixed_effect":{
                    "coef":-0.9170016542,
                    "weight":2.625,
                    "ci_lower":-1.7288138098,
                    "ci_upper":-0.1051894985
                },
                "random_effect":{
                    "coef":-1.0899672504,
                    "weight":2.625,
                    "ci_lower":-1.8245733744,
                    "ci_upper":-0.3553611264
                }
            },
            {
                "study_id":"Alfano2018",
                "fixed_effect":{
                    "coef":-0.9170016542,
                    "weight":4.634404,
                    "ci_lower":-1.7288138098,
                    "ci_upper":-0.1051894985
                },
                "random_effect":{
                    "coef":-1.0899672504,
                    "weight":4.634404,
                    "ci_lower":-1.8245733744,
                    "ci_upper":-0.3553611264
                }
            },
            {
                "study_id":"Alfano2020",
                "fixed_effect":{
                    "coef":-0.9170016542,
                    "weight":3.27247272,
                    "ci_lower":-1.7288138098,
                    "ci_upper":-0.1051894985
                },
                "random_effect":{
                    "coef":-1.0899672504,
                    "weight":3.27247272,
                    "ci_lower":-1.8245733744,
                    "ci_upper":-0.3553611264
                }
            },
            {
                "study_id":"Gathogo2017",
                "fixed_effect":{
                    "coef":-0.9170016542,
                    "weight":6.864,
                    "ci_lower":-1.7288138098,
                    "ci_upper":-0.1051894985
                },
                "random_effect":{
                    "coef":-1.0899672504,
                    "weight":6.864,
                    "ci_lower":-1.8245733744,
                    "ci_upper":-0.3553611264
                }
            },
            {
                "study_id":"Izzo2018",
                "fixed_effect":{
                    "coef":-0.9170016542,
                    "weight":5.717712,
                    "ci_lower":-1.7288138098,
                    "ci_upper":-0.1051894985
                },
                "random_effect":{
                    "coef":-1.0899672504,
                    "weight":5.717712,
                    "ci_lower":-1.8245733744,
                    "ci_upper":-0.3553611264
                }
            },
            {
                "study_id":"Locke2015",
                "fixed_effect":{
                    "coef":-0.9170016542,
                    "weight":106.06631725,
                    "ci_lower":-1.7288138098,
                    "ci_upper":-0.1051894985
                },
                "random_effect":{
                    "coef":-1.0899672504,
                    "weight":106.06631725,
                    "ci_lower":-1.8245733744,
                    "ci_upper":-0.3553611264
                }
            },
            {
                "study_id":"Mazuecos2011",
                "fixed_effect":{
                    "coef":-0.9170016542,
                    "weight":3.80928,
                    "ci_lower":-1.7288138098,
                    "ci_upper":-0.1051894985
                },
                "random_effect":{
                    "coef":-1.0899672504,
                    "weight":3.80928,
                    "ci_lower":-1.8245733744,
                    "ci_upper":-0.3553611264
                }
            },
            {
                "study_id":"Mazuecos2012",
                "fixed_effect":{
                    "coef":-0.9170016542,
                    "weight":1.875,
                    "ci_lower":-1.7288138098,
                    "ci_upper":-0.1051894985
                },
                "random_effect":{
                    "coef":-1.0899672504,
                    "weight":1.875,
                    "ci_lower":-1.8245733744,
                    "ci_upper":-0.3553611264
                }
            },
            {
                "study_id":"Qiu2006",
                "fixed_effect":{
                    "coef":-0.9170016542,
                    "weight":8.633562,
                    "ci_lower":-1.7288138098,
                    "ci_upper":-0.1051894985
                },
                "random_effect":{
                    "coef":-1.0899672504,
                    "weight":8.633562,
                    "ci_lower":-1.8245733744,
                    "ci_upper":-0.3553611264
                }
            },
            {
                "study_id":"Roland2016",
                "fixed_effect":{
                    "coef":-0.9170016542,
                    "weight":31.91265,
                    "ci_lower":-1.7288138098,
                    "ci_upper":-0.1051894985
                },
                "random_effect":{
                    "coef":-1.0899672504,
                    "weight":31.91265,
                    "ci_lower":-1.8245733744,
                    "ci_upper":-0.3553611264
                }
            }
        ],
        "fixed_effects":{
            "coef":[
                1.0708956195,
                -0.9170016542
            ],
            "pvalues":[
                0.0000146294,
                0.0577229862
            ],
            "rsquared":0.3799237219,
            "aic":5.7515317758,
            "bic":6.3567019618
        },
        "random_effects":{
            "coef":[
                1.3493015971,
                -1.0899672504,
                1.0
            ],
            "pvalues":[
                1.807639616e-71,
                0.0036358813,
                null
            ],
            "group_variance":0.0605973983,
            "log_likelihood":-3.9431796231
        }
    },
    {
        "variable":"hbv",
        "studies involved":[
            "Ailioaie2017",
            "Alfano2018",
            "Alfano2020",
            "Gathogo2017",
            "Mazuecos2011",
            "Muller2015",
            "Roland2016"
        ],
        "studies_details":[
            {
                "study_id":"Ailioaie2017",
                "fixed_effect":{
                    "coef":2.8165444297,
                    "weight":2.625,
                    "ci_lower":-6.6666475141,
                    "ci_upper":12.2997363735
                },
                "random_effect":{
                    "coef":-0.2401236371,
                    "weight":2.625,
                    "ci_lower":-1.153791944,
                    "ci_upper":0.6735446698
                }
            },
            {
                "study_id":"Alfano2018",
                "fixed_effect":{
                    "coef":2.8165444297,
                    "weight":4.634404,
                    "ci_lower":-6.6666475141,
                    "ci_upper":12.2997363735
                },
                "random_effect":{
                    "coef":-0.2401236371,
                    "weight":4.634404,
                    "ci_lower":-1.153791944,
                    "ci_upper":0.6735446698
                }
            },
            {
                "study_id":"Alfano2020",
                "fixed_effect":{
                    "coef":2.8165444297,
                    "weight":3.27247272,
                    "ci_lower":-6.6666475141,
                    "ci_upper":12.2997363735
                },
                "random_effect":{
                    "coef":-0.2401236371,
                    "weight":3.27247272,
                    "ci_lower":-1.153791944,
                    "ci_upper":0.6735446698
                }
            },
            {
                "study_id":"Gathogo2017",
                "fixed_effect":{
                    "coef":2.8165444297,
                    "weight":6.864,
                    "ci_lower":-6.6666475141,
                    "ci_upper":12.2997363735
                },
                "random_effect":{
                    "coef":-0.2401236371,
                    "weight":6.864,
                    "ci_lower":-1.153791944,
                    "ci_upper":0.6735446698
                }
            },
            {
                "study_id":"Mazuecos2011",
                "fixed_effect":{
                    "coef":2.8165444297,
                    "weight":3.80928,
                    "ci_lower":-6.6666475141,
                    "ci_upper":12.2997363735
                },
                "random_effect":{
                    "coef":-0.2401236371,
                    "weight":3.80928,
                    "ci_lower":-1.153791944,
                    "ci_upper":0.6735446698
                }
            },
            {
                "study_id":"Muller2015",
                "fixed_effect":{
                    "coef":2.8165444297,
                    "weight":3.6288,
                    "ci_lower":-6.6666475141,
                    "ci_upper":12.2997363735
                },
                "random_effect":{
                    "coef":-0.2401236371,
                    "weight":3.6288,
                    "ci_lower":-1.153791944,
                    "ci_upper":0.6735446698
                }
            },
            {
                "study_id":"Roland2016",
                "fixed_effect":{
                    "coef":2.8165444297,
                    "weight":31.91265,
                    "ci_lower":-6.6666475141,
                    "ci_upper":12.2997363735
                },
                "random_effect":{
                    "coef":-0.2401236371,
                    "weight":31.91265,
                    "ci_lower":-1.153791944,
                    "ci_upper":0.6735446698
                }
            }
        ],
        "fixed_effects":{
            "coef":[
                0.8400015723,
                2.8165444297
            ],
            "pvalues":[
                0.0418647308,
                0.5857405692
            ],
            "rsquared":0.0634726642,
            "aic":13.0892842522,
            "bic":12.9811045503
        },
        "random_effects":{
            "coef":[
                1.2407180068,
                -0.2401236371,
                1.0
            ],
            "pvalues":[
                0.0000015998,
                0.6064741307,
                null
            ],
            "group_variance":0.1809006349,
            "log_likelihood":-3.2890433888
        }
    },
    {
        "variable":"cd4",
        "studies involved":[
            "Ailioaie2017",
            "Alfano2018",
            "Izzo2018",
            "Muller2015",
            "Roland2016"
        ],
        "studies_details":[
            {
                "study_id":"Ailioaie2017",
                "fixed_effect":{
                    "coef":-0.0020988109,
                    "weight":2.625,
                    "ci_lower":-0.0064423854,
                    "ci_upper":0.0022447635
                },
                "random_effect":{
                    "coef":-0.0034614367,
                    "weight":2.625,
                    "ci_lower":-0.0048905578,
                    "ci_upper":-0.0020323156
                }
            },
            {
                "study_id":"Alfano2018",
                "fixed_effect":{
                    "coef":-0.0020988109,
                    "weight":4.634404,
                    "ci_lower":-0.0064423854,
                    "ci_upper":0.0022447635
                },
                "random_effect":{
                    "coef":-0.0034614367,
                    "weight":4.634404,
                    "ci_lower":-0.0048905578,
                    "ci_upper":-0.0020323156
                }
            },
            {
                "study_id":"Izzo2018",
                "fixed_effect":{
                    "coef":-0.0020988109,
                    "weight":5.717712,
                    "ci_lower":-0.0064423854,
                    "ci_upper":0.0022447635
                },
                "random_effect":{
                    "coef":-0.0034614367,
                    "weight":5.717712,
                    "ci_lower":-0.0048905578,
                    "ci_upper":-0.0020323156
                }
            },
            {
                "study_id":"Muller2015",
                "fixed_effect":{
                    "coef":-0.0020988109,
                    "weight":3.6288,
                    "ci_lower":-0.0064423854,
                    "ci_upper":0.0022447635
                },
                "random_effect":{
                    "coef":-0.0034614367,
                    "weight":3.6288,
                    "ci_lower":-0.0048905578,
                    "ci_upper":-0.0020323156
                }
            },
            {
                "study_id":"Roland2016",
                "fixed_effect":{
                    "coef":-0.0020988109,
                    "weight":31.91265,
                    "ci_lower":-0.0064423854,
                    "ci_upper":0.0022447635
                },
                "random_effect":{
                    "coef":-0.0034614367,
                    "weight":31.91265,
                    "ci_lower":-0.0048905578,
                    "ci_upper":-0.0020323156
                }
            }
        ],
        "fixed_effects":{
            "coef":[
                1.8790174249,
                -0.0020988109
            ],
            "pvalues":[
                0.1709256557,
                0.4134726756
            ],
            "rsquared":0.2301655569,
            "aic":9.4116598102,
            "bic":8.6305356351
        },
        "random_effects":{
            "coef":[
                2.4677474593,
                -0.0034614367,
                1.0
            ],
            "pvalues":[
                0.0,
                0.0000020619,
                null
            ],
            "group_variance":0.2295711065,
            "log_likelihood":-9.0739102493
        }
    },
    {
        "variable":"viral_suppress_pre",
        "studies involved":[
            "Ailioaie2017",
            "Alfano2018",
            "Gathogo2017",
            "Izzo2018",
            "Mazuecos2011",
            "Muller2015",
            "Roland2016"
        ],
        "studies_details":[
            {
                "study_id":"Ailioaie2017",
                "fixed_effect":{
                    "coef":-3.3194554649,
                    "weight":2.625,
                    "ci_lower":-9.9866951249,
                    "ci_upper":3.3477841951
                },
                "random_effect":{
                    "coef":-3.1294675102,
                    "weight":2.625,
                    "ci_lower":-3.3248722399,
                    "ci_upper":-2.9340627805
                }
            },
            {
                "study_id":"Alfano2018",
                "fixed_effect":{
                    "coef":-3.3194554649,
                    "weight":4.634404,
                    "ci_lower":-9.9866951249,
                    "ci_upper":3.3477841951
                },
                "random_effect":{
                    "coef":-3.1294675102,
                    "weight":4.634404,
                    "ci_lower":-3.3248722399,
                    "ci_upper":-2.9340627805
                }
            },
            {
                "study_id":"Gathogo2017",
                "fixed_effect":{
                    "coef":-3.3194554649,
                    "weight":6.864,
                    "ci_lower":-9.9866951249,
                    "ci_upper":3.3477841951
                },
                "random_effect":{
                    "coef":-3.1294675102,
                    "weight":6.864,
                    "ci_lower":-3.3248722399,
                    "ci_upper":-2.9340627805
                }
            },
            {
                "study_id":"Izzo2018",
                "fixed_effect":{
                    "coef":-3.3194554649,
                    "weight":5.717712,
                    "ci_lower":-9.9866951249,
                    "ci_upper":3.3477841951
                },
                "random_effect":{
                    "coef":-3.1294675102,
                    "weight":5.717712,
                    "ci_lower":-3.3248722399,
                    "ci_upper":-2.9340627805
                }
            },
            {
                "study_id":"Mazuecos2011",
                "fixed_effect":{
                    "coef":-3.3194554649,
                    "weight":3.80928,
                    "ci_lower":-9.9866951249,
                    "ci_upper":3.3477841951
                },
                "random_effect":{
                    "coef":-3.1294675102,
                    "weight":3.80928,
                    "ci_lower":-3.3248722399,
                    "ci_upper":-2.9340627805
                }
            },
            {
                "study_id":"Muller2015",
                "fixed_effect":{
                    "coef":-3.3194554649,
                    "weight":3.6288,
                    "ci_lower":-9.9866951249,
                    "ci_upper":3.3477841951
                },
                "random_effect":{
                    "coef":-3.1294675102,
                    "weight":3.6288,
                    "ci_lower":-3.3248722399,
                    "ci_upper":-2.9340627805
                }
            },
            {
                "study_id":"Roland2016",
                "fixed_effect":{
                    "coef":-3.3194554649,
                    "weight":31.91265,
                    "ci_lower":-9.9866951249,
                    "ci_upper":3.3477841951
                },
                "random_effect":{
                    "coef":-3.1294675102,
                    "weight":31.91265,
                    "ci_lower":-3.3248722399,
                    "ci_upper":-2.9340627805
                }
            }
        ],
        "fixed_effects":{
            "coef":[
                4.2136387376,
                -3.3194554649
            ],
            "pvalues":[
                0.2630347573,
                0.3739627413
            ],
            "rsquared":0.1599823616,
            "aic":10.9856764661,
            "bic":10.8774967643
        },
        "random_effects":{
            "coef":[
                4.1328371134,
                -3.1294675102,
                1.0
            ],
            "pvalues":[
                6.296841128e-42,
                2.769699532e-216,
                null
            ],
            "group_variance":0.1534246145,
            "log_likelihood":-3.266176778
        }
    },
    {
        "variable":"viral_suppress_post",
        "studies involved":[
            "Ailioaie2017",
            "Alfano2018",
            "Izzo2018",
            "Mazuecos2011",
            "Muller2015"
        ],
        "studies_details":[
            {
                "study_id":"Ailioaie2017",
                "fixed_effect":{
                    "coef":-0.7207733885,
                    "weight":2.625,
                    "ci_lower":-10.8865866862,
                    "ci_upper":9.4450399092
                },
                "random_effect":{
                    "coef":-0.7553922626,
                    "weight":2.625,
                    "ci_lower":-3.1139405268,
                    "ci_upper":1.6031560016
                }
            },
            {
                "study_id":"Alfano2018",
                "fixed_effect":{
                    "coef":-0.7207733885,
                    "weight":4.634404,
                    "ci_lower":-10.8865866862,
                    "ci_upper":9.4450399092
                },
                "random_effect":{
                    "coef":-0.7553922626,
                    "weight":4.634404,
                    "ci_lower":-3.1139405268,
                    "ci_upper":1.6031560016
                }
            },
            {
                "study_id":"Izzo2018",
                "fixed_effect":{
                    "coef":-0.7207733885,
                    "weight":5.717712,
                    "ci_lower":-10.8865866862,
                    "ci_upper":9.4450399092
                },
                "random_effect":{
                    "coef":-0.7553922626,
                    "weight":5.717712,
                    "ci_lower":-3.1139405268,
                    "ci_upper":1.6031560016
                }
            },
            {
                "study_id":"Mazuecos2011",
                "fixed_effect":{
                    "coef":-0.7207733885,
                    "weight":3.80928,
                    "ci_lower":-10.8865866862,
                    "ci_upper":9.4450399092
                },
                "random_effect":{
                    "coef":-0.7553922626,
                    "weight":3.80928,
                    "ci_lower":-3.1139405268,
                    "ci_upper":1.6031560016
                }
            },
            {
                "study_id":"Muller2015",
                "fixed_effect":{
                    "coef":-0.7207733885,
                    "weight":3.6288,
                    "ci_lower":-10.8865866862,
                    "ci_upper":9.4450399092
                },
                "random_effect":{
                    "coef":-0.7553922626,
                    "weight":3.6288,
                    "ci_lower":-3.1139405268,
                    "ci_upper":1.6031560016
                }
            }
        ],
        "fixed_effects":{
            "coef":[
                1.7427391729,
                -0.7207733885
            ],
            "pvalues":[
                0.7426088287,
                0.8982802805
            ],
            "rsquared":0.0063961316,
            "aic":12.2434298051,
            "bic":11.46230563
        },
        "random_effects":{
            "coef":[
                1.8867078095,
                -0.7553922626,
                1.0
            ],
            "pvalues":[
                0.0186809615,
                0.5301704582,
                null
            ],
            "group_variance":0.2730445036,
            "log_likelihood":-2.0852653367
        }
    },
    {
        "variable":"atg",
        "studies involved":[
            "Alfano2020",
            "Locke2015",
            "Mazuecos2011",
            "Muller2015",
            "Qiu2006"
        ],
        "studies_details":[
            {
                "study_id":"Alfano2020",
                "fixed_effect":{
                    "coef":0.8256177121,
                    "weight":3.27247272,
                    "ci_lower":-0.3404204393,
                    "ci_upper":1.9916558635
                },
                "random_effect":{
                    "coef":0.6392714397,
                    "weight":3.27247272,
                    "ci_lower":-0.2335079653,
                    "ci_upper":1.5120508447
                }
            },
            {
                "study_id":"Locke2015",
                "fixed_effect":{
                    "coef":0.8256177121,
                    "weight":106.06631725,
                    "ci_lower":-0.3404204393,
                    "ci_upper":1.9916558635
                },
                "random_effect":{
                    "coef":0.6392714397,
                    "weight":106.06631725,
                    "ci_lower":-0.2335079653,
                    "ci_upper":1.5120508447
                }
            },
            {
                "study_id":"Mazuecos2011",
                "fixed_effect":{
                    "coef":0.8256177121,
                    "weight":3.80928,
                    "ci_lower":-0.3404204393,
                    "ci_upper":1.9916558635
                },
                "random_effect":{
                    "coef":0.6392714397,
                    "weight":3.80928,
                    "ci_lower":-0.2335079653,
                    "ci_upper":1.5120508447
                }
            },
            {
                "study_id":"Muller2015",
                "fixed_effect":{
                    "coef":0.8256177121,
                    "weight":3.6288,
                    "ci_lower":-0.3404204393,
                    "ci_upper":1.9916558635
                },
                "random_effect":{
                    "coef":0.6392714397,
                    "weight":3.6288,
                    "ci_lower":-0.2335079653,
                    "ci_upper":1.5120508447
                }
            },
            {
                "study_id":"Qiu2006",
                "fixed_effect":{
                    "coef":0.8256177121,
                    "weight":8.633562,
                    "ci_lower":-0.3404204393,
                    "ci_upper":1.9916558635
                },
                "random_effect":{
                    "coef":0.6392714397,
                    "weight":8.633562,
                    "ci_lower":-0.2335079653,
                    "ci_upper":1.5120508447
                }
            }
        ],
        "fixed_effects":{
            "coef":[
                0.6926192796,
                0.8256177121
            ],
            "pvalues":[
                0.0170507286,
                0.2593148626
            ],
            "rsquared":0.3909802099,
            "aic":4.5635080795,
            "bic":3.7823839044
        },
        "random_effects":{
            "coef":[
                0.9568220611,
                0.6392714397,
                1.0
            ],
            "pvalues":[
                0.0000045624,
                0.1511129626,
                null
            ],
            "group_variance":0.0842739012,
            "log_likelihood":-2.1875210462
        }
    },
    {
        "variable":"il_2",
        "studies involved":[
            "Ailioaie2017",
            "Alfano2018",
            "Alfano2020",
            "Mazuecos2011",
            "Qiu2006"
        ],
        "studies_details":[
            {
                "study_id":"Ailioaie2017",
                "fixed_effect":{
                    "coef":0.4176442982,
                    "weight":2.625,
                    "ci_lower":-1.5392565822,
                    "ci_upper":2.3745451787
                },
                "random_effect":{
                    "coef":0.5457251608,
                    "weight":2.625,
                    "ci_lower":-1.5605322824,
                    "ci_upper":2.651982604
                }
            },
            {
                "study_id":"Alfano2018",
                "fixed_effect":{
                    "coef":0.4176442982,
                    "weight":4.634404,
                    "ci_lower":-1.5392565822,
                    "ci_upper":2.3745451787
                },
                "random_effect":{
                    "coef":0.5457251608,
                    "weight":4.634404,
                    "ci_lower":-1.5605322824,
                    "ci_upper":2.651982604
                }
            },
            {
                "study_id":"Alfano2020",
                "fixed_effect":{
                    "coef":0.4176442982,
                    "weight":3.27247272,
                    "ci_lower":-1.5392565822,
                    "ci_upper":2.3745451787
                },
                "random_effect":{
                    "coef":0.5457251608,
                    "weight":3.27247272,
                    "ci_lower":-1.5605322824,
                    "ci_upper":2.651982604
                }
            },
            {
                "study_id":"Mazuecos2011",
                "fixed_effect":{
                    "coef":0.4176442982,
                    "weight":3.80928,
                    "ci_lower":-1.5392565822,
                    "ci_upper":2.3745451787
                },
                "random_effect":{
                    "coef":0.5457251608,
                    "weight":3.80928,
                    "ci_lower":-1.5605322824,
                    "ci_upper":2.651982604
                }
            },
            {
                "study_id":"Qiu2006",
                "fixed_effect":{
                    "coef":0.4176442982,
                    "weight":8.633562,
                    "ci_lower":-1.5392565822,
                    "ci_upper":2.3745451787
                },
                "random_effect":{
                    "coef":0.5457251608,
                    "weight":8.633562,
                    "ci_lower":-1.5605322824,
                    "ci_upper":2.651982604
                }
            }
        ],
        "fixed_effects":{
            "coef":[
                0.6383082839,
                0.4176442982
            ],
            "pvalues":[
                0.4387235396,
                0.7038635213
            ],
            "rsquared":0.0551120607,
            "aic":11.9771139199,
            "bic":11.1959897447
        },
        "random_effects":{
            "coef":[
                0.6947837941,
                0.5457251608,
                1.0
            ],
            "pvalues":[
                0.4111133428,
                0.6115723698,
                0.9999999941
            ],
            "group_variance":0.264534298,
            "log_likelihood":-3.7162920112
        }
    },
    {
        "variable":"induction_use",
        "studies involved":[
            "Ailioaie2017",
            "Alfano2018",
            "Alfano2020",
            "Mazuecos2012",
            "Muller2015",
            "Qiu2006"
        ],
        "studies_details":[
            {
                "study_id":"Ailioaie2017",
                "fixed_effect":{
                    "coef":0.5341163587,
                    "weight":2.625,
                    "ci_lower":-1.3603596498,
                    "ci_upper":2.4285923672
                },
                "random_effect":{
                    "coef":0.3717579451,
                    "weight":2.625,
                    "ci_lower":-0.2006727412,
                    "ci_upper":0.9441886315
                }
            },
            {
                "study_id":"Alfano2018",
                "fixed_effect":{
                    "coef":0.5341163587,
                    "weight":4.634404,
                    "ci_lower":-1.3603596498,
                    "ci_upper":2.4285923672
                },
                "random_effect":{
                    "coef":0.3717579451,
                    "weight":4.634404,
                    "ci_lower":-0.2006727412,
                    "ci_upper":0.9441886315
                }
            },
            {
                "study_id":"Alfano2020",
                "fixed_effect":{
                    "coef":0.5341163587,
                    "weight":3.27247272,
                    "ci_lower":-1.3603596498,
                    "ci_upper":2.4285923672
                },
                "random_effect":{
                    "coef":0.3717579451,
                    "weight":3.27247272,
                    "ci_lower":-0.2006727412,
                    "ci_upper":0.9441886315
                }
            },
            {
                "study_id":"Mazuecos2012",
                "fixed_effect":{
                    "coef":0.5341163587,
                    "weight":1.875,
                    "ci_lower":-1.3603596498,
                    "ci_upper":2.4285923672
                },
                "random_effect":{
                    "coef":0.3717579451,
                    "weight":1.875,
                    "ci_lower":-0.2006727412,
                    "ci_upper":0.9441886315
                }
            },
            {
                "study_id":"Muller2015",
                "fixed_effect":{
                    "coef":0.5341163587,
                    "weight":3.6288,
                    "ci_lower":-1.3603596498,
                    "ci_upper":2.4285923672
                },
                "random_effect":{
                    "coef":0.3717579451,
                    "weight":3.6288,
                    "ci_lower":-0.2006727412,
                    "ci_upper":0.9441886315
                }
            },
            {
                "study_id":"Qiu2006",
                "fixed_effect":{
                    "coef":0.5341163587,
                    "weight":8.633562,
                    "ci_lower":-1.3603596498,
                    "ci_upper":2.4285923672
                },
                "random_effect":{
                    "coef":0.3717579451,
                    "weight":8.633562,
                    "ci_lower":-0.2006727412,
                    "ci_upper":0.9441886315
                }
            }
        ],
        "fixed_effects":{
            "coef":[
                0.594789426,
                0.5341163587
            ],
            "pvalues":[
                0.5000699887,
                0.6099692072
            ],
            "rsquared":0.0709245631,
            "aic":14.6804489527,
            "bic":14.2639678912
        },
        "random_effects":{
            "coef":[
                0.9083018888,
                0.3717579451,
                1.0
            ],
            "pvalues":[
                0.0583503532,
                0.2030544271,
                null
            ],
            "group_variance":0.2341039578,
            "log_likelihood":-4.9499386174
        }
    },
    {
        "variable":"ii_pre",
        "studies involved":[
            "Ailioaie2017",
            "Alfano2018",
            "Alfano2020",
            "Izzo2018",
            "Mazuecos2012"
        ],
        "studies_details":[
            {
                "study_id":"Ailioaie2017",
                "fixed_effect":{
                    "coef":0.5730422518,
                    "weight":2.625,
                    "ci_lower":-1.451496685,
                    "ci_upper":2.5975811886
                },
                "random_effect":{
                    "coef":0.5129936428,
                    "weight":2.625,
                    "ci_lower":0.5129936428,
                    "ci_upper":0.5129936428
                }
            },
            {
                "study_id":"Alfano2018",
                "fixed_effect":{
                    "coef":0.5730422518,
                    "weight":4.634404,
                    "ci_lower":-1.451496685,
                    "ci_upper":2.5975811886
                },
                "random_effect":{
                    "coef":0.5129936428,
                    "weight":4.634404,
                    "ci_lower":0.5129936428,
                    "ci_upper":0.5129936428
                }
            },
            {
                "study_id":"Alfano2020",
                "fixed_effect":{
                    "coef":0.5730422518,
                    "weight":3.27247272,
                    "ci_lower":-1.451496685,
                    "ci_upper":2.5975811886
                },
                "random_effect":{
                    "coef":0.5129936428,
                    "weight":3.27247272,
                    "ci_lower":0.5129936428,
                    "ci_upper":0.5129936428
                }
            },
            {
                "study_id":"Izzo2018",
                "fixed_effect":{
                    "coef":0.5730422518,
                    "weight":5.717712,
                    "ci_lower":-1.451496685,
                    "ci_upper":2.5975811886
                },
                "random_effect":{
                    "coef":0.5129936428,
                    "weight":5.717712,
                    "ci_lower":0.5129936428,
                    "ci_upper":0.5129936428
                }
            },
            {
                "study_id":"Mazuecos2012",
                "fixed_effect":{
                    "coef":0.5730422518,
                    "weight":1.875,
                    "ci_lower":-1.451496685,
                    "ci_upper":2.5975811886
                },
                "random_effect":{
                    "coef":0.5129936428,
                    "weight":1.875,
                    "ci_lower":0.5129936428,
                    "ci_upper":0.5129936428
                }
            }
        ],
        "fixed_effects":{
            "coef":[
                0.7893779709,
                0.5730422518
            ],
            "pvalues":[
                0.2375461759,
                0.6177282008
            ],
            "rsquared":0.0930458956,
            "aic":12.0239531338,
            "bic":11.2428289586
        },
        "random_effects":{
            "coef":[
                0.9378705522,
                0.5129936428,
                1.0
            ],
            "pvalues":[
                0.0019892856,
                0.0,
                null
            ],
            "group_variance":0.2300357617,
            "log_likelihood":-3.5610714979
        }
    },
    {
        "variable":"ii_post",
        "studies involved":[
            "Ailioaie2017",
            "Alfano2018",
            "Alfano2020",
            "Izzo2018",
            "Mazuecos2012"
        ],
        "studies_details":[
            {
                "study_id":"Ailioaie2017",
                "fixed_effect":{
                    "coef":-0.8274542943,
                    "weight":2.625,
                    "ci_lower":-4.506505872,
                    "ci_upper":2.8515972834
                },
                "random_effect":{
                    "coef":-0.5401550914,
                    "weight":2.625,
                    "ci_lower":-3.6113504536,
                    "ci_upper":2.5310402708
                }
            },
            {
                "study_id":"Alfano2018",
                "fixed_effect":{
                    "coef":-0.8274542943,
                    "weight":4.634404,
                    "ci_lower":-4.506505872,
                    "ci_upper":2.8515972834
                },
                "random_effect":{
                    "coef":-0.5401550914,
                    "weight":4.634404,
                    "ci_lower":-3.6113504536,
                    "ci_upper":2.5310402708
                }
            },
            {
                "study_id":"Alfano2020",
                "fixed_effect":{
                    "coef":-0.8274542943,
                    "weight":3.27247272,
                    "ci_lower":-4.506505872,
                    "ci_upper":2.8515972834
                },
                "random_effect":{
                    "coef":-0.5401550914,
                    "weight":3.27247272,
                    "ci_lower":-3.6113504536,
                    "ci_upper":2.5310402708
                }
            },
            {
                "study_id":"Izzo2018",
                "fixed_effect":{
                    "coef":-0.8274542943,
                    "weight":5.717712,
                    "ci_lower":-4.506505872,
                    "ci_upper":2.8515972834
                },
                "random_effect":{
                    "coef":-0.5401550914,
                    "weight":5.717712,
                    "ci_lower":-3.6113504536,
                    "ci_upper":2.5310402708
                }
            },
            {
                "study_id":"Mazuecos2012",
                "fixed_effect":{
                    "coef":-0.8274542943,
                    "weight":1.875,
                    "ci_lower":-4.506505872,
                    "ci_upper":2.8515972834
                },
                "random_effect":{
                    "coef":-0.5401550914,
                    "weight":1.875,
                    "ci_lower":-3.6113504536,
                    "ci_upper":2.5310402708
                }
            }
        ],
        "fixed_effects":{
            "coef":[
                1.6903671425,
                -0.8274542943
            ],
            "pvalues":[
                0.3459068661,
                0.6891739102
            ],
            "rsquared":0.0608344147,
            "aic":12.1984529268,
            "bic":11.4173287516
        },
        "random_effects":{
            "coef":[
                1.5535902156,
                -0.5401550914,
                1.0
            ],
            "pvalues":[
                0.1938557371,
                0.7303045103,
                0.9999999941
            ],
            "group_variance":0.242820703,
            "log_likelihood":-3.1678426245
        }
    },
    {
        "variable":"pi_pre",
        "studies involved":[
            "Alfano2018",
            "Izzo2018",
            "Mazuecos2012",
            "Muller2015"
        ],
        "studies_details":[
            {
                "study_id":"Alfano2018",
                "fixed_effect":{
                    "coef":-2.5899766467,
                    "weight":4.634404,
                    "ci_lower":-5.8316295314,
                    "ci_upper":0.651676238
                },
                "random_effect":{
                    "coef":-2.7338892088,
                    "weight":4.634404,
                    "ci_lower":-5.5220539248,
                    "ci_upper":0.0542755071
                }
            },
            {
                "study_id":"Izzo2018",
                "fixed_effect":{
                    "coef":-2.5899766467,
                    "weight":5.717712,
                    "ci_lower":-5.8316295314,
                    "ci_upper":0.651676238
                },
                "random_effect":{
                    "coef":-2.7338892088,
                    "weight":5.717712,
                    "ci_lower":-5.5220539248,
                    "ci_upper":0.0542755071
                }
            },
            {
                "study_id":"Mazuecos2012",
                "fixed_effect":{
                    "coef":-2.5899766467,
                    "weight":1.875,
                    "ci_lower":-5.8316295314,
                    "ci_upper":0.651676238
                },
                "random_effect":{
                    "coef":-2.7338892088,
                    "weight":1.875,
                    "ci_lower":-5.5220539248,
                    "ci_upper":0.0542755071
                }
            },
            {
                "study_id":"Muller2015",
                "fixed_effect":{
                    "coef":-2.5899766467,
                    "weight":3.6288,
                    "ci_lower":-5.8316295314,
                    "ci_upper":0.651676238
                },
                "random_effect":{
                    "coef":-2.7338892088,
                    "weight":3.6288,
                    "ci_lower":-5.5220539248,
                    "ci_upper":0.0542755071
                }
            }
        ],
        "fixed_effects":{
            "coef":[
                2.5443033167,
                -2.5899766467
            ],
            "pvalues":[
                0.1374631916,
                0.2578461146
            ],
            "rsquared":0.5507923897,
            "aic":6.6809100549,
            "bic":5.4534987771
        },
        "random_effects":{
            "coef":[
                2.5969937607,
                -2.7338892088,
                1.0
            ],
            "pvalues":[
                0.004270194,
                0.0546251544,
                null
            ],
            "group_variance":0.08830587,
            "log_likelihood":-0.5076036936
        }
    },
    {
        "variable":"pi_post",
        "studies involved":[
            "Alfano2018",
            "Izzo2018",
            "Mazuecos2012",
            "Muller2015"
        ],
        "studies_details":[
            {
                "study_id":"Alfano2018",
                "fixed_effect":{
                    "coef":4.3476852255,
                    "weight":4.634404,
                    "ci_lower":-0.7283590306,
                    "ci_upper":9.4237294815
                },
                "random_effect":{
                    "coef":3.590695908,
                    "weight":4.634404,
                    "ci_lower":0.4681544407,
                    "ci_upper":6.7132373753
                }
            },
            {
                "study_id":"Izzo2018",
                "fixed_effect":{
                    "coef":4.3476852255,
                    "weight":5.717712,
                    "ci_lower":-0.7283590306,
                    "ci_upper":9.4237294815
                },
                "random_effect":{
                    "coef":3.590695908,
                    "weight":5.717712,
                    "ci_lower":0.4681544407,
                    "ci_upper":6.7132373753
                }
            },
            {
                "study_id":"Mazuecos2012",
                "fixed_effect":{
                    "coef":4.3476852255,
                    "weight":1.875,
                    "ci_lower":-0.7283590306,
                    "ci_upper":9.4237294815
                },
                "random_effect":{
                    "coef":3.590695908,
                    "weight":1.875,
                    "ci_lower":0.4681544407,
                    "ci_upper":6.7132373753
                }
            },
            {
                "study_id":"Muller2015",
                "fixed_effect":{
                    "coef":4.3476852255,
                    "weight":3.6288,
                    "ci_lower":-0.7283590306,
                    "ci_upper":9.4237294815
                },
                "random_effect":{
                    "coef":3.590695908,
                    "weight":3.6288,
                    "ci_lower":0.4681544407,
                    "ci_upper":6.7132373753
                }
            }
        ],
        "fixed_effects":{
            "coef":[
                -0.4042728559,
                4.3476852255
            ],
            "pvalues":[
                0.6728451787,
                0.2352056328
            ],
            "rsquared":0.5849104241,
            "aic":6.3649467663,
            "bic":5.1375354885
        },
        "random_effects":{
            "coef":[
                -0.0581919051,
                3.590695908,
                1.0
            ],
            "pvalues":[
                0.931003928,
                0.0242051245,
                null
            ],
            "group_variance":0.1247631314,
            "log_likelihood":-0.4318652168
        }
    },
    {
        "variable":"nrti_pre",
        "studies involved":[
            "Ailioaie2017",
            "Alfano2018",
            "Izzo2018"
        ],
        "studies_details":[
            {
                "study_id":"Ailioaie2017",
                "fixed_effect":{
                    "coef":-1.6345458834,
                    "weight":2.625,
                    "ci_lower":-13.4938429578,
                    "ci_upper":10.2247511911
                },
                "random_effect":{
                    "coef":-3.1556316944,
                    "weight":2.625,
                    "ci_lower":-7.0821762372,
                    "ci_upper":0.7709128484
                }
            },
            {
                "study_id":"Alfano2018",
                "fixed_effect":{
                    "coef":-1.6345458834,
                    "weight":4.634404,
                    "ci_lower":-13.4938429578,
                    "ci_upper":10.2247511911
                },
                "random_effect":{
                    "coef":-3.1556316944,
                    "weight":4.634404,
                    "ci_lower":-7.0821762372,
                    "ci_upper":0.7709128484
                }
            },
            {
                "study_id":"Izzo2018",
                "fixed_effect":{
                    "coef":-1.6345458834,
                    "weight":5.717712,
                    "ci_lower":-13.4938429578,
                    "ci_upper":10.2247511911
                },
                "random_effect":{
                    "coef":-3.1556316944,
                    "weight":5.717712,
                    "ci_lower":-7.0821762372,
                    "ci_upper":0.7709128484
                }
            }
        ],
        "fixed_effects":{
            "coef":[
                2.2026328984,
                -1.6345458834
            ],
            "pvalues":[
                0.727208756,
                0.8320307918
            ],
            "rsquared":0.0680139343,
            "aic":9.2498476382,
            "bic":7.4470722155
        },
        "random_effects":{
            "coef":[
                3.4739874928,
                -3.1556316944,
                1.0
            ],
            "pvalues":[
                0.0002957569,
                0.1152135102,
                null
            ],
            "group_variance":0.5472606794,
            "log_likelihood":-0.2040228633
        }
    },
    {
        "variable":"nrti_post",
        "studies involved":[
            "Ailioaie2017",
            "Alfano2018",
            "Izzo2018"
        ],
        "studies_details":[
            {
                "study_id":"Ailioaie2017",
                "fixed_effect":{
                    "coef":-23.1870404763,
                    "weight":2.625,
                    "ci_lower":-26.1409001682,
                    "ci_upper":-20.2331807845
                },
                "random_effect":{
                    "coef":-23.0211225682,
                    "weight":2.625,
                    "ci_lower":-23.0623119084,
                    "ci_upper":-22.9799332279
                }
            },
            {
                "study_id":"Alfano2018",
                "fixed_effect":{
                    "coef":-23.1870404763,
                    "weight":4.634404,
                    "ci_lower":-26.1409001682,
                    "ci_upper":-20.2331807845
                },
                "random_effect":{
                    "coef":-23.0211225682,
                    "weight":4.634404,
                    "ci_lower":-23.0623119084,
                    "ci_upper":-22.9799332279
                }
            },
            {
                "study_id":"Izzo2018",
                "fixed_effect":{
                    "coef":-23.1870404763,
                    "weight":5.717712,
                    "ci_lower":-26.1409001682,
                    "ci_upper":-20.2331807845
                },
                "random_effect":{
                    "coef":-23.0211225682,
                    "weight":5.717712,
                    "ci_lower":-23.0623119084,
                    "ci_upper":-22.9799332279
                }
            }
        ],
        "fixed_effects":{
            "coef":[
                17.4346168828,
                -23.1870404763
            ],
            "pvalues":[
                0.0391953999,
                0.0413197942
            ],
            "rsquared":0.9957932556,
            "aic":-6.9520388307,
            "bic":-8.7548142534
        },
        "random_effects":{
            "coef":[
                17.30983441,
                -23.0211225682,
                1.0
            ],
            "pvalues":[
                0.0,
                0.0,
                null
            ],
            "group_variance":0.0018811253,
            "log_likelihood":3.8066065218
        }
    },
    {
        "variable":"nnrti_pre",
        "studies involved":[
            "Ailioaie2017",
            "Alfano2018",
            "Izzo2018",
            "Mazuecos2012",
            "Muller2015"
        ],
        "studies_details":[
            {
                "study_id":"Ailioaie2017",
                "fixed_effect":{
                    "coef":2.49175433,
                    "weight":2.625,
                    "ci_lower":-0.2851226583,
                    "ci_upper":5.2686313183
                },
                "random_effect":{
                    "coef":2.1433453408,
                    "weight":2.625,
                    "ci_lower":1.5910999137,
                    "ci_upper":2.695590768
                }
            },
            {
                "study_id":"Alfano2018",
                "fixed_effect":{
                    "coef":2.49175433,
                    "weight":4.634404,
                    "ci_lower":-0.2851226583,
                    "ci_upper":5.2686313183
                },
                "random_effect":{
                    "coef":2.1433453408,
                    "weight":4.634404,
                    "ci_lower":1.5910999137,
                    "ci_upper":2.695590768
                }
            },
            {
                "study_id":"Izzo2018",
                "fixed_effect":{
                    "coef":2.49175433,
                    "weight":5.717712,
                    "ci_lower":-0.2851226583,
                    "ci_upper":5.2686313183
                },
                "random_effect":{
                    "coef":2.1433453408,
                    "weight":5.717712,
                    "ci_lower":1.5910999137,
                    "ci_upper":2.695590768
                }
            },
            {
                "study_id":"Mazuecos2012",
                "fixed_effect":{
                    "coef":2.49175433,
                    "weight":1.875,
                    "ci_lower":-0.2851226583,
                    "ci_upper":5.2686313183
                },
                "random_effect":{
                    "coef":2.1433453408,
                    "weight":1.875,
                    "ci_lower":1.5910999137,
                    "ci_upper":2.695590768
                }
            },
            {
                "study_id":"Muller2015",
                "fixed_effect":{
                    "coef":2.49175433,
                    "weight":3.6288,
                    "ci_lower":-0.2851226583,
                    "ci_upper":5.2686313183
                },
                "random_effect":{
                    "coef":2.1433453408,
                    "weight":3.6288,
                    "ci_lower":1.5910999137,
                    "ci_upper":2.695590768
                }
            }
        ],
        "fixed_effects":{
            "coef":[
                0.3508173101,
                2.49175433
            ],
            "pvalues":[
                0.5118476247,
                0.1768579073
            ],
            "rsquared":0.5076486187,
            "aic":9.4423718619,
            "bic":8.6612476867
        },
        "random_effects":{
            "coef":[
                0.5718163342,
                2.1433453408,
                1.0
            ],
            "pvalues":[
                0.0006307432,
                0.0,
                null
            ],
            "group_variance":0.1597684855,
            "log_likelihood":-2.396759172
        }
    },
    {
        "variable":"nnrti_post",
        "studies involved":[
            "Ailioaie2017",
            "Alfano2018",
            "Izzo2018",
            "Mazuecos2012"
        ],
        "studies_details":[
            {
                "study_id":"Ailioaie2017",
                "fixed_effect":{
                    "coef":3.9140257093,
                    "weight":2.625,
                    "ci_lower":-7.7066278093,
                    "ci_upper":15.534679228
                },
                "random_effect":{
                    "coef":5.6844969858,
                    "weight":2.625,
                    "ci_lower":4.1239853137,
                    "ci_upper":7.2450086578
                }
            },
            {
                "study_id":"Alfano2018",
                "fixed_effect":{
                    "coef":3.9140257093,
                    "weight":4.634404,
                    "ci_lower":-7.7066278093,
                    "ci_upper":15.534679228
                },
                "random_effect":{
                    "coef":5.6844969858,
                    "weight":4.634404,
                    "ci_lower":4.1239853137,
                    "ci_upper":7.2450086578
                }
            },
            {
                "study_id":"Izzo2018",
                "fixed_effect":{
                    "coef":3.9140257093,
                    "weight":5.717712,
                    "ci_lower":-7.7066278093,
                    "ci_upper":15.534679228
                },
                "random_effect":{
                    "coef":5.6844969858,
                    "weight":5.717712,
                    "ci_lower":4.1239853137,
                    "ci_upper":7.2450086578
                }
            },
            {
                "study_id":"Mazuecos2012",
                "fixed_effect":{
                    "coef":3.9140257093,
                    "weight":1.875,
                    "ci_lower":-7.7066278093,
                    "ci_upper":15.534679228
                },
                "random_effect":{
                    "coef":5.6844969858,
                    "weight":1.875,
                    "ci_lower":4.1239853137,
                    "ci_upper":7.2450086578
                }
            }
        ],
        "fixed_effects":{
            "coef":[
                -0.0363856962,
                3.9140257093
            ],
            "pvalues":[
                0.9829673606,
                0.577012648
            ],
            "rsquared":0.1789183,
            "aic":10.1801791414,
            "bic":8.9527678636
        },
        "random_effects":{
            "coef":[
                -0.4593551414,
                5.6844969858,
                1.0
            ],
            "pvalues":[
                0.0002220819,
                0.0,
                null
            ],
            "group_variance":0.2332397129,
            "log_likelihood":-0.608528144
        }
    },
    {
        "variable":"ii_shift",
        "studies involved":[
            "Ailioaie2017",
            "Alfano2018",
            "Alfano2020",
            "Izzo2018",
            "Mazuecos2012"
        ],
        "studies_details":[
            {
                "study_id":"Ailioaie2017",
                "fixed_effect":{
                    "coef":-0.5712124274,
                    "weight":2.625,
                    "ci_lower":-2.0401979991,
                    "ci_upper":0.8977731442
                },
                "random_effect":{
                    "coef":-0.4357040878,
                    "weight":2.625,
                    "ci_lower":-0.6999058473,
                    "ci_upper":-0.1715023282
                }
            },
            {
                "study_id":"Alfano2018",
                "fixed_effect":{
                    "coef":-0.5712124274,
                    "weight":4.634404,
                    "ci_lower":-2.0401979991,
                    "ci_upper":0.8977731442
                },
                "random_effect":{
                    "coef":-0.4357040878,
                    "weight":4.634404,
                    "ci_lower":-0.6999058473,
                    "ci_upper":-0.1715023282
                }
            },
            {
                "study_id":"Alfano2020",
                "fixed_effect":{
                    "coef":-0.5712124274,
                    "weight":3.27247272,
                    "ci_lower":-2.0401979991,
                    "ci_upper":0.8977731442
                },
                "random_effect":{
                    "coef":-0.4357040878,
                    "weight":3.27247272,
                    "ci_lower":-0.6999058473,
                    "ci_upper":-0.1715023282
                }
            },
            {
                "study_id":"Izzo2018",
                "fixed_effect":{
                    "coef":-0.5712124274,
                    "weight":5.717712,
                    "ci_lower":-2.0401979991,
                    "ci_upper":0.8977731442
                },
                "random_effect":{
                    "coef":-0.4357040878,
                    "weight":5.717712,
                    "ci_lower":-0.6999058473,
                    "ci_upper":-0.1715023282
                }
            },
            {
                "study_id":"Mazuecos2012",
                "fixed_effect":{
                    "coef":-0.5712124274,
                    "weight":1.875,
                    "ci_lower":-2.0401979991,
                    "ci_upper":0.8977731442
                },
                "random_effect":{
                    "coef":-0.4357040878,
                    "weight":1.875,
                    "ci_lower":-0.6999058473,
                    "ci_upper":-0.1715023282
                }
            }
        ],
        "fixed_effects":{
            "coef":[
                1.5041996238,
                -0.5712124274
            ],
            "pvalues":[
                0.1133496357,
                0.5014171363
            ],
            "rsquared":0.1622127132,
            "aic":11.6273150669,
            "bic":10.8461908918
        },
        "random_effects":{
            "coef":[
                1.5041996238,
                -0.4357040878,
                1.0
            ],
            "pvalues":[
                0.0001994821,
                0.0012279698,
                null
            ],
            "group_variance":0.2271272704,
            "log_likelihood":-3.7663164167
        }
    },
    {
        "variable":"pi_avoid",
        "studies involved":[
            "Alfano2018",
            "Izzo2018",
            "Mazuecos2012",
            "Muller2015"
        ],
        "studies_details":[
            {
                "study_id":"Alfano2018",
                "fixed_effect":{
                    "coef":-0.9427020339,
                    "weight":4.634404,
                    "ci_lower":-1.8680617258,
                    "ci_upper":-0.017342342
                },
                "random_effect":{
                    "coef":-0.8822040783,
                    "weight":4.634404,
                    "ci_lower":-1.6859097415,
                    "ci_upper":-0.0784984152
                }
            },
            {
                "study_id":"Izzo2018",
                "fixed_effect":{
                    "coef":-0.9427020339,
                    "weight":5.717712,
                    "ci_lower":-1.8680617258,
                    "ci_upper":-0.017342342
                },
                "random_effect":{
                    "coef":-0.8822040783,
                    "weight":5.717712,
                    "ci_lower":-1.6859097415,
                    "ci_upper":-0.0784984152
                }
            },
            {
                "study_id":"Mazuecos2012",
                "fixed_effect":{
                    "coef":-0.9427020339,
                    "weight":1.875,
                    "ci_lower":-1.8680617258,
                    "ci_upper":-0.017342342
                },
                "random_effect":{
                    "coef":-0.8822040783,
                    "weight":1.875,
                    "ci_lower":-1.6859097415,
                    "ci_upper":-0.0784984152
                }
            },
            {
                "study_id":"Muller2015",
                "fixed_effect":{
                    "coef":-0.9427020339,
                    "weight":3.6288,
                    "ci_lower":-1.8680617258,
                    "ci_upper":-0.017342342
                },
                "random_effect":{
                    "coef":-0.8822040783,
                    "weight":3.6288,
                    "ci_lower":-1.6859097415,
                    "ci_upper":-0.0784984152
                }
            }
        ],
        "fixed_effects":{
            "coef":[
                1.6582280766,
                -0.9427020339
            ],
            "pvalues":[
                0.057199783,
                0.1839487651
            ],
            "rsquared":0.665939618,
            "aic":5.4962564402,
            "bic":4.2688451625
        },
        "random_effects":{
            "coef":[
                1.6582280766,
                -0.8822040783,
                1.0
            ],
            "pvalues":[
                0.0000525633,
                0.0314419302,
                null
            ],
            "group_variance":0.0840721045,
            "log_likelihood":-1.6042499293
        }
    },
    {
        "variable":"viral_breakthrough",
        "studies involved":[
            "Ailioaie2017",
            "Alfano2018",
            "Izzo2018",
            "Mazuecos2011",
            "Muller2015"
        ],
        "studies_details":[
            {
                "study_id":"Ailioaie2017",
                "fixed_effect":{
                    "coef":-0.2177661176,
                    "weight":2.625,
                    "ci_lower":-1.5675488485,
                    "ci_upper":1.1320166132
                },
                "random_effect":{
                    "coef":-0.3315014411,
                    "weight":2.625,
                    "ci_lower":-1.7446328872,
                    "ci_upper":1.0816300049
                }
            },
            {
                "study_id":"Alfano2018",
                "fixed_effect":{
                    "coef":-0.2177661176,
                    "weight":4.634404,
                    "ci_lower":-1.5675488485,
                    "ci_upper":1.1320166132
                },
                "random_effect":{
                    "coef":-0.3315014411,
                    "weight":4.634404,
                    "ci_lower":-1.7446328872,
                    "ci_upper":1.0816300049
                }
            },
            {
                "study_id":"Izzo2018",
                "fixed_effect":{
                    "coef":-0.2177661176,
                    "weight":5.717712,
                    "ci_lower":-1.5675488485,
                    "ci_upper":1.1320166132
                },
                "random_effect":{
                    "coef":-0.3315014411,
                    "weight":5.717712,
                    "ci_lower":-1.7446328872,
                    "ci_upper":1.0816300049
                }
            },
            {
                "study_id":"Mazuecos2011",
                "fixed_effect":{
                    "coef":-0.2177661176,
                    "weight":3.80928,
                    "ci_lower":-1.5675488485,
                    "ci_upper":1.1320166132
                },
                "random_effect":{
                    "coef":-0.3315014411,
                    "weight":3.80928,
                    "ci_lower":-1.7446328872,
                    "ci_upper":1.0816300049
                }
            },
            {
                "study_id":"Muller2015",
                "fixed_effect":{
                    "coef":-0.2177661176,
                    "weight":3.6288,
                    "ci_lower":-1.5675488485,
                    "ci_upper":1.1320166132
                },
                "random_effect":{
                    "coef":-0.3315014411,
                    "weight":3.6288,
                    "ci_lower":-1.7446328872,
                    "ci_upper":1.0816300049
                }
            }
        ],
        "fixed_effects":{
            "coef":[
                1.1326572692,
                -0.2177661176
            ],
            "pvalues":[
                0.0529712802,
                0.7725636772
            ],
            "rsquared":0.0322555506,
            "aic":12.1115770522,
            "bic":11.3304528771
        },
        "random_effects":{
            "coef":[
                1.2463925927,
                -0.3315014411,
                1.0
            ],
            "pvalues":[
                0.0,
                0.6456674102,
                null
            ],
            "group_variance":0.2599099963,
            "log_likelihood":-3.9685537373
        }
    }
]