{
    "Pooled_Survival_Proportion": 0.19789606737790508,
    "95%_CI": [
        0.11739423585303192,
        0.31396403735715406
    ],
    "I2": 84.46497685022845,
    "Q": 25.74827189786856,
    "p_value_for_Q": 3.556638651391886e-05,
    "tau2": 0.37288807915963756,
    "combined_results": [
        {
            "study_id": "Durand2021",
            "sample_size": 75,
            "effect_size": 0.36,
            "ci_lb": 0.2598272025066089,
            "ci_ub": 0.47405795969736997,
            "weight_percent": 23.068139853206283
        },
        {
            "study_id": "Durand2024",
            "sample_size": 198,
            "effect_size": 0.17000000000000004,
            "ci_lb": 0.12385234439042687,
            "ci_ub": 0.2288510872674676,
            "weight_percent": 24.31425684803004
        },
        {
            "study_id": "Matignon2019",
            "sample_size": 61,
            "effect_size": 0.08000000000000002,
            "ci_lb": 0.03333096188470911,
            "ci_ub": 0.17985581743476006,
            "weight_percent": 16.68297161282811
        },
        {
            "study_id": "Muller2015",
            "sample_size": 27,
            "effect_size": 0.08000000000000002,
            "ci_lb": 0.021191565452312298,
            "ci_ub": 0.2588486421400638,
            "weight_percent": 11.341967335703156
        },
        {
            "study_id": "Stock2010",
            "sample_size": 150,
            "effect_size": 0.31,
            "ci_lb": 0.241194400912979,
            "ci_ub": 0.38838729215405327,
            "weight_percent": 24.59266435023241
        },
        {
            "study_id": "Pooled Estimate",
            "sample_size": 511,
            "effect_size": 0.19789606737790508,
            "ci_lb": 0.11739423585303192,
            "ci_ub": 0.31396403735715406,
            "weight_percent": 100.0
        }
    ]
}